[
  {
    "UserID": "148",
    "Nickname": "뽕",
    "Cool": "7724",
    "Good": "571",
    "Bad": "0",
    "Miss": "8",
    "MaxCombo": "2305",
    "Acc": "98.51%",
    "Progress": "S",
    "Clear": "Clear"
  },
  {
    "UserID": "1166",
    "Nickname": "Delly.K",
    "Cool": "7602",
    "Good": "686",
    "Bad": "0",
    "Miss": "15",
    "MaxCombo": "2297",
    "Acc": "97.63%",
    "Progress": "S",
    "Clear": "Clear"
  },
  {
    "UserID": "6022",
    "Nickname": "retyxrk",
    "Cool": "7554",
    "Good": "722",
    "Bad": "0",
    "Miss": "27",
    "MaxCombo": "2605",
    "Acc": "96.29%",
    "Progress": "S",
    "Clear": "Clear"
  },
  {
    "UserID": "5408",
    "Nickname": "LCnanoda",
    "Cool": "7325",
    "Good": "948",
    "Bad": "0",
    "Miss": "30",
    "MaxCombo": "1966",
    "Acc": "95.72%",
    "Progress": "A",
    "Clear": "Clear"
  },
  {
    "UserID": "1200",
    "Nickname": "무",
    "Cool": "7006",
    "Good": "1269",
    "Bad": "0",
    "Miss": "28",
    "MaxCombo": "1776",
    "Acc": "95.59%",
    "Progress": "A",
    "Clear": "Clear"
  },
  {
    "UserID": "152",
    "Nickname": "tomlee3",
    "Cool": "7683",
    "Good": "584",
    "Bad": "0",
    "Miss": "36",
    "MaxCombo": "1318",
    "Acc": "95.46%",
    "Progress": "A",
    "Clear": "Clear"
  },
  {
    "UserID": "1173",
    "Nickname": "SuperPlay",
    "Cool": "7219",
    "Good": "1052",
    "Bad": "4",
    "Miss": "28",
    "MaxCombo": "1549",
    "Acc": "95.39%",
    "Progress": "A",
    "Clear": "Clear"
  },
  {
    "UserID": "5390",
    "Nickname": "Myzki",
    "Cool": "7436",
    "Good": "802",
    "Bad": "0",
    "Miss": "65",
    "MaxCombo": "1022",
    "Acc": "92.08%",
    "Progress": "A",
    "Clear": "Clear"
  },
  {
    "UserID": "1181",
    "Nickname": "못하는톰",
    "Cool": "6366",
    "Good": "1880",
    "Bad": "13",
    "Miss": "44",
    "MaxCombo": "992",
    "Acc": "91.78%",
    "Progress": "A",
    "Clear": "Clear"
  },
  {
    "UserID": "6335",
    "Nickname": "시아",
    "Cool": "6763",
    "Good": "1469",
    "Bad": "0",
    "Miss": "71",
    "MaxCombo": "766",
    "Acc": "90.71%",
    "Progress": "A",
    "Clear": "Clear"
  },
  {
    "UserID": "5929",
    "Nickname": "Azrael",
    "Cool": "7491",
    "Good": "731",
    "Bad": "3",
    "Miss": "78",
    "MaxCombo": "1155",
    "Acc": "90.43%",
    "Progress": "A",
    "Clear": "Clear"
  },
  {
    "UserID": "5546",
    "Nickname": "allenkalbo",
    "Cool": "7482",
    "Good": "736",
    "Bad": "3",
    "Miss": "82",
    "MaxCombo": "1734",
    "Acc": "89.99%",
    "Progress": "B",
    "Clear": "Clear"
  },
  {
    "UserID": "1202",
    "Nickname": "뜌",
    "Cool": "7261",
    "Good": "959",
    "Bad": "12",
    "Miss": "71",
    "MaxCombo": "1786",
    "Acc": "89.96%",
    "Progress": "B",
    "Clear": "Clear"
  },
  {
    "UserID": "6424",
    "Nickname": "Dipif",
    "Cool": "7021",
    "Good": "1200",
    "Bad": "7",
    "Miss": "75",
    "MaxCombo": "1253",
    "Acc": "89.81%",
    "Progress": "B",
    "Clear": "Clear"
  },
  {
    "UserID": "1183",
    "Nickname": "SacredReisen",
    "Cool": "7011",
    "Good": "1201",
    "Bad": "4",
    "Miss": "87",
    "MaxCombo": "1261",
    "Acc": "88.83%",
    "Progress": "B",
    "Clear": "Clear"
  },
  {
    "UserID": "167",
    "Nickname": "rights",
    "Cool": "7030",
    "Good": "1176",
    "Bad": "21",
    "Miss": "76",
    "MaxCombo": "761",
    "Acc": "88.21%",
    "Progress": "B",
    "Clear": "Clear"
  },
  {
    "UserID": "1204",
    "Nickname": "거미",
    "Cool": "7174",
    "Good": "1024",
    "Bad": "7",
    "Miss": "98",
    "MaxCombo": "776",
    "Acc": "87.51%",
    "Progress": "B",
    "Clear": "Clear"
  },
  {
    "UserID": "5383",
    "Nickname": "NLwI",
    "Cool": "6731",
    "Good": "1470",
    "Bad": "4",
    "Miss": "98",
    "MaxCombo": "1084",
    "Acc": "87.35%",
    "Progress": "B",
    "Clear": "Clear"
  },
  {
    "UserID": "6114",
    "Nickname": "noobbb",
    "Cool": "6878",
    "Good": "1313",
    "Bad": "20",
    "Miss": "92",
    "MaxCombo": "760",
    "Acc": "86.44%",
    "Progress": "B",
    "Clear": "Clear"
  },
  {
    "UserID": "2260",
    "Nickname": "짜이우",
    "Cool": "7284",
    "Good": "893",
    "Bad": "18",
    "Miss": "108",
    "MaxCombo": "836",
    "Acc": "85.37%",
    "Progress": "C",
    "Clear": "Clear"
  },
  {
    "UserID": "165",
    "Nickname": "Chess",
    "Cool": "7050",
    "Good": "1111",
    "Bad": "6",
    "Miss": "136",
    "MaxCombo": "488",
    "Acc": "83.4%",
    "Progress": "C",
    "Clear": "Clear"
  },
  {
    "UserID": "5501",
    "Nickname": "Angelina",
    "Cool": "6904",
    "Good": "1258",
    "Bad": "13",
    "Miss": "128",
    "MaxCombo": "1116",
    "Acc": "83.35%",
    "Progress": "C",
    "Clear": "Clear"
  },
  {
    "UserID": "97",
    "Nickname": "Nazo",
    "Cool": "7019",
    "Good": "1140",
    "Bad": "22",
    "Miss": "122",
    "MaxCombo": "755",
    "Acc": "83.16%",
    "Progress": "C",
    "Clear": "Clear"
  },
  {
    "UserID": "5618",
    "Nickname": "Hades",
    "Cool": "6251",
    "Good": "1911",
    "Bad": "5",
    "Miss": "136",
    "MaxCombo": "780",
    "Acc": "82.64%",
    "Progress": "C",
    "Clear": "Clear"
  },
  {
    "UserID": "1207",
    "Nickname": "짬찌포병",
    "Cool": "6367",
    "Good": "1792",
    "Bad": "25",
    "Miss": "119",
    "MaxCombo": "538",
    "Acc": "82.45%",
    "Progress": "C",
    "Clear": "Clear"
  },
  {
    "UserID": "5463",
    "Nickname": "Nyooo",
    "Cool": "6368",
    "Good": "1786",
    "Bad": "2",
    "Miss": "147",
    "MaxCombo": "749",
    "Acc": "81.91%",
    "Progress": "C",
    "Clear": "Clear"
  },
  {
    "UserID": "5397",
    "Nickname": "nadekodayo",
    "Cool": "7078",
    "Good": "1068",
    "Bad": "4",
    "Miss": "153",
    "MaxCombo": "929",
    "Acc": "81.82%",
    "Progress": "C",
    "Clear": "Clear"
  },
  {
    "UserID": "6065",
    "Nickname": "LASvegas",
    "Cool": "7011",
    "Good": "1130",
    "Bad": "40",
    "Miss": "122",
    "MaxCombo": "596",
    "Acc": "81.22%",
    "Progress": "C",
    "Clear": "Clear"
  },
  {
    "UserID": "5633",
    "Nickname": "LL",
    "Cool": "7012",
    "Good": "1128",
    "Bad": "38",
    "Miss": "125",
    "MaxCombo": "831",
    "Acc": "81.11%",
    "Progress": "C",
    "Clear": "Clear"
  },
  {
    "UserID": "5359",
    "Nickname": "WaKa",
    "Cool": "7078",
    "Good": "1060",
    "Bad": "48",
    "Miss": "117",
    "MaxCombo": "760",
    "Acc": "80.97%",
    "Progress": "C",
    "Clear": "Clear"
  },
  {
    "UserID": "5512",
    "Nickname": "DancingASDF",
    "Cool": "7063",
    "Good": "1073",
    "Bad": "8",
    "Miss": "159",
    "MaxCombo": "759",
    "Acc": "80.73%",
    "Progress": "C",
    "Clear": "Clear"
  },
  {
    "UserID": "4348",
    "Nickname": "nadavv",
    "Cool": "6333",
    "Good": "1810",
    "Bad": "26",
    "Miss": "134",
    "MaxCombo": "493",
    "Acc": "80.69%",
    "Progress": "C",
    "Clear": "Clear"
  },
  {
    "UserID": "5377",
    "Nickname": "o2jaaamE",
    "Cool": "6260",
    "Good": "1876",
    "Bad": "34",
    "Miss": "133",
    "MaxCombo": "630",
    "Acc": "79.86%",
    "Progress": "C",
    "Clear": "Clear"
  },
  {
    "UserID": "2257",
    "Nickname": "LunaticAnt",
    "Cool": "6751",
    "Good": "1368",
    "Bad": "30",
    "Miss": "154",
    "MaxCombo": "1094",
    "Acc": "78.57%",
    "Progress": "C",
    "Clear": "Clear"
  },
  {
    "UserID": "2301",
    "Nickname": "Midnight",
    "Cool": "6955",
    "Good": "1155",
    "Bad": "16",
    "Miss": "177",
    "MaxCombo": "741",
    "Acc": "77.83%",
    "Progress": "D",
    "Clear": "Clear"
  },
  {
    "UserID": "6229",
    "Nickname": "FenIndraWijaya",
    "Cool": "6465",
    "Good": "1645",
    "Bad": "46",
    "Miss": "147",
    "MaxCombo": "737",
    "Acc": "77.3%",
    "Progress": "D",
    "Clear": "Clear"
  },
  {
    "UserID": "5931",
    "Nickname": "Xyphoes",
    "Cool": "6843",
    "Good": "1259",
    "Bad": "31",
    "Miss": "170",
    "MaxCombo": "394",
    "Acc": "76.85%",
    "Progress": "D",
    "Clear": "Clear"
  },
  {
    "UserID": "2328",
    "Nickname": "Sgathaich바니",
    "Cool": "6825",
    "Good": "1277",
    "Bad": "18",
    "Miss": "183",
    "MaxCombo": "539",
    "Acc": "76.83%",
    "Progress": "D",
    "Clear": "Clear"
  },
  {
    "UserID": "2322",
    "Nickname": "GyphN",
    "Cool": "6859",
    "Good": "1233",
    "Bad": "46",
    "Miss": "165",
    "MaxCombo": "447",
    "Acc": "75.79%",
    "Progress": "D",
    "Clear": "Clear"
  },
  {
    "UserID": "5428",
    "Nickname": "푸푸민우",
    "Cool": "6735",
    "Good": "1358",
    "Bad": "23",
    "Miss": "187",
    "MaxCombo": "537",
    "Acc": "75.77%",
    "Progress": "D",
    "Clear": "Clear"
  },
  {
    "UserID": "5529",
    "Nickname": "ZYuan",
    "Cool": "6186",
    "Good": "1912",
    "Bad": "39",
    "Miss": "166",
    "MaxCombo": "505",
    "Acc": "75.71%",
    "Progress": "D",
    "Clear": "Clear"
  },
  {
    "UserID": "4338",
    "Nickname": "CratyII",
    "Cool": "6689",
    "Good": "1390",
    "Bad": "34",
    "Miss": "190",
    "MaxCombo": "641",
    "Acc": "74.21%",
    "Progress": "D",
    "Clear": "Clear"
  },
  {
    "UserID": "1225",
    "Nickname": "Bazzi",
    "Cool": "6898",
    "Good": "1175",
    "Bad": "25",
    "Miss": "205",
    "MaxCombo": "453",
    "Acc": "73.8%",
    "Progress": "D",
    "Clear": "Clear"
  },
  {
    "UserID": "2265",
    "Nickname": "제아롯드",
    "Cool": "6750",
    "Good": "1323",
    "Bad": "43",
    "Miss": "187",
    "MaxCombo": "696",
    "Acc": "73.64%",
    "Progress": "D",
    "Clear": "Clear"
  },
  {
    "UserID": "6025",
    "Nickname": "넨시",
    "Cool": "6724",
    "Good": "1348",
    "Bad": "40",
    "Miss": "191",
    "MaxCombo": "514",
    "Acc": "73.5%",
    "Progress": "D",
    "Clear": "Clear"
  },
  {
    "UserID": "5822",
    "Nickname": "실존하는허수",
    "Cool": "6019",
    "Good": "2049",
    "Bad": "47",
    "Miss": "188",
    "MaxCombo": "533",
    "Acc": "72.31%",
    "Progress": "D",
    "Clear": "Clear"
  },
  {
    "UserID": "2300",
    "Nickname": "grimmmsenpai",
    "Cool": "6667",
    "Good": "1379",
    "Bad": "49",
    "Miss": "208",
    "MaxCombo": "597",
    "Acc": "70.65%",
    "Progress": "D",
    "Clear": "Clear"
  },
  {
    "UserID": "5631",
    "Nickname": "hainanshuaige",
    "Cool": "6609",
    "Good": "1430",
    "Bad": "71",
    "Miss": "193",
    "MaxCombo": "673",
    "Acc": "69.83%",
    "Progress": "D",
    "Clear": "Clear"
  },
  {
    "UserID": "1174",
    "Nickname": "GUMI",
    "Cool": "6614",
    "Good": "1424",
    "Bad": "67",
    "Miss": "198",
    "MaxCombo": "479",
    "Acc": "69.73%",
    "Progress": "D",
    "Clear": "Clear"
  },
  {
    "UserID": "5605",
    "Nickname": "제노",
    "Cool": "6463",
    "Good": "1574",
    "Bad": "69",
    "Miss": "197",
    "MaxCombo": "501",
    "Acc": "69.46%",
    "Progress": "D",
    "Clear": "Clear"
  },
  {
    "UserID": "5780",
    "Nickname": "ririri",
    "Cool": "6330",
    "Good": "1699",
    "Bad": "77",
    "Miss": "197",
    "MaxCombo": "809",
    "Acc": "68.46%",
    "Progress": "D",
    "Clear": "Clear"
  },
  {
    "UserID": "5365",
    "Nickname": "LaserMan",
    "Cool": "6336",
    "Good": "1641",
    "Bad": "127",
    "Miss": "199",
    "MaxCombo": "757",
    "Acc": "62.88%",
    "Progress": "D",
    "Clear": "Clear"
  },
  {
    "UserID": "5577",
    "Nickname": "Sweetsoul",
    "Cool": "6947",
    "Good": "1087",
    "Bad": "10",
    "Miss": "215",
    "MaxCombo": "770",
    "Acc": "55.73%",
    "Progress": "D",
    "Clear": "Failed"
  },
  {
    "UserID": "2271",
    "Nickname": "sorakara",
    "Cool": "6680",
    "Good": "634",
    "Bad": "4",
    "Miss": "115",
    "MaxCombo": "1000",
    "Acc": "7.82%",
    "Progress": "F",
    "Clear": "Failed"
  },
  {
    "UserID": "5431",
    "Nickname": "SSU",
    "Cool": "5135",
    "Good": "889",
    "Bad": "12",
    "Miss": "152",
    "MaxCombo": "888",
    "Acc": "6.44%",
    "Progress": "F",
    "Clear": "Failed"
  },
  {
    "UserID": "4332",
    "Nickname": "mentor",
    "Cool": "4077",
    "Good": "999",
    "Bad": "40",
    "Miss": "145",
    "MaxCombo": "359",
    "Acc": "5.42%",
    "Progress": "F",
    "Clear": "Failed"
  },
  {
    "UserID": "2317",
    "Nickname": "Up",
    "Cool": "3800",
    "Good": "1235",
    "Bad": "30",
    "Miss": "147",
    "MaxCombo": "358",
    "Acc": "5.38%",
    "Progress": "F",
    "Clear": "Failed"
  },
  {
    "UserID": "5813",
    "Nickname": "스알",
    "Cool": "4043",
    "Good": "954",
    "Bad": "40",
    "Miss": "129",
    "MaxCombo": "453",
    "Acc": "5.34%",
    "Progress": "F",
    "Clear": "Failed"
  },
  {
    "UserID": "5827",
    "Nickname": "워너비",
    "Cool": "3775",
    "Good": "1117",
    "Bad": "73",
    "Miss": "136",
    "MaxCombo": "376",
    "Acc": "5.23%",
    "Progress": "F",
    "Clear": "Failed"
  },
  {
    "UserID": "5730",
    "Nickname": "IrritableTing",
    "Cool": "4020",
    "Good": "842",
    "Bad": "33",
    "Miss": "130",
    "MaxCombo": "568",
    "Acc": "5.2%",
    "Progress": "F",
    "Clear": "Failed"
  },
  {
    "UserID": "72",
    "Nickname": "햇살",
    "Cool": "4285",
    "Good": "481",
    "Bad": "0",
    "Miss": "34",
    "MaxCombo": "4749",
    "Acc": "5.1%",
    "Progress": "F",
    "Clear": "Failed"
  },
  {
    "UserID": "6138",
    "Nickname": "ChnGyf",
    "Cool": "3333",
    "Good": "788",
    "Bad": "27",
    "Miss": "122",
    "MaxCombo": "335",
    "Acc": "4.4%",
    "Progress": "F",
    "Clear": "Failed"
  },
  {
    "UserID": "5361",
    "Nickname": "2Coma",
    "Cool": "2995",
    "Good": "672",
    "Bad": "46",
    "Miss": "110",
    "MaxCombo": "228",
    "Acc": "3.92%",
    "Progress": "F",
    "Clear": "Failed"
  },
  {
    "UserID": "2313",
    "Nickname": "KenZ",
    "Cool": "3087",
    "Good": "525",
    "Bad": "3",
    "Miss": "83",
    "MaxCombo": "658",
    "Acc": "3.86%",
    "Progress": "F",
    "Clear": "Failed"
  },
  {
    "UserID": "2233",
    "Nickname": "Bero",
    "Cool": "2956",
    "Good": "657",
    "Bad": "3",
    "Miss": "92",
    "MaxCombo": "427",
    "Acc": "3.86%",
    "Progress": "F",
    "Clear": "Failed"
  },
  {
    "UserID": "3333",
    "Nickname": "kraiz19",
    "Cool": "2742",
    "Good": "654",
    "Bad": "29",
    "Miss": "116",
    "MaxCombo": "299",
    "Acc": "3.63%",
    "Progress": "F",
    "Clear": "Failed"
  },
  {
    "UserID": "5740",
    "Nickname": "DOG10DUK",
    "Cool": "2791",
    "Good": "601",
    "Bad": "24",
    "Miss": "113",
    "MaxCombo": "304",
    "Acc": "3.62%",
    "Progress": "F",
    "Clear": "Failed"
  },
  {
    "UserID": "2319",
    "Nickname": "spherical",
    "Cool": "2721",
    "Good": "665",
    "Bad": "8",
    "Miss": "117",
    "MaxCombo": "284",
    "Acc": "3.62%",
    "Progress": "F",
    "Clear": "Failed"
  },
  {
    "UserID": "5550",
    "Nickname": "Meow",
    "Cool": "2709",
    "Good": "656",
    "Bad": "39",
    "Miss": "108",
    "MaxCombo": "367",
    "Acc": "3.6%",
    "Progress": "F",
    "Clear": "Failed"
  },
  {
    "UserID": "4326",
    "Nickname": "BananenTropfen",
    "Cool": "2606",
    "Good": "681",
    "Bad": "45",
    "Miss": "105",
    "MaxCombo": "305",
    "Acc": "3.51%",
    "Progress": "F",
    "Clear": "Failed"
  },
  {
    "UserID": "6266",
    "Nickname": "Harambe",
    "Cool": "2529",
    "Good": "547",
    "Bad": "29",
    "Miss": "105",
    "MaxCombo": "271",
    "Acc": "3.29%",
    "Progress": "F",
    "Clear": "Failed"
  },
  {
    "UserID": "5475",
    "Nickname": "shibatachun",
    "Cool": "2485",
    "Good": "581",
    "Bad": "40",
    "Miss": "101",
    "MaxCombo": "249",
    "Acc": "3.28%",
    "Progress": "F",
    "Clear": "Failed"
  },
  {
    "UserID": "2263",
    "Nickname": "Eve",
    "Cool": "2503",
    "Good": "555",
    "Bad": "18",
    "Miss": "102",
    "MaxCombo": "327",
    "Acc": "3.27%",
    "Progress": "F",
    "Clear": "Failed"
  },
  {
    "UserID": "43",
    "Nickname": "BS",
    "Cool": "2513",
    "Good": "496",
    "Bad": "22",
    "Miss": "104",
    "MaxCombo": "315",
    "Acc": "3.22%",
    "Progress": "F",
    "Clear": "Failed"
  },
  {
    "UserID": "5821",
    "Nickname": "NewsTimeK",
    "Cool": "2212",
    "Good": "761",
    "Bad": "42",
    "Miss": "94",
    "MaxCombo": "277",
    "Acc": "3.17%",
    "Progress": "F",
    "Clear": "Failed"
  },
  {
    "UserID": "5389",
    "Nickname": "Takumi",
    "Cool": "2092",
    "Good": "860",
    "Bad": "42",
    "Miss": "91",
    "MaxCombo": "284",
    "Acc": "3.15%",
    "Progress": "F",
    "Clear": "Failed"
  },
  {
    "UserID": "2237",
    "Nickname": "모모로",
    "Cool": "2467",
    "Good": "423",
    "Bad": "8",
    "Miss": "53",
    "MaxCombo": "607",
    "Acc": "3.09%",
    "Progress": "F",
    "Clear": "Failed"
  },
  {
    "UserID": "2283",
    "Nickname": "Tapsilog",
    "Cool": "2244",
    "Good": "552",
    "Bad": "20",
    "Miss": "103",
    "MaxCombo": "280",
    "Acc": "2.99%",
    "Progress": "F",
    "Clear": "Failed"
  },
  {
    "UserID": "2324",
    "Nickname": "FullOptions",
    "Cool": "2080",
    "Good": "403",
    "Bad": "27",
    "Miss": "86",
    "MaxCombo": "274",
    "Acc": "2.65%",
    "Progress": "F",
    "Clear": "Failed"
  },
  {
    "UserID": "2266",
    "Nickname": "료슬",
    "Cool": "1756",
    "Good": "371",
    "Bad": "32",
    "Miss": "69",
    "MaxCombo": "369",
    "Acc": "2.27%",
    "Progress": "F",
    "Clear": "Failed"
  },
  {
    "UserID": "4342",
    "Nickname": "HassanAli",
    "Cool": "1557",
    "Good": "544",
    "Bad": "30",
    "Miss": "70",
    "MaxCombo": "277",
    "Acc": "2.24%",
    "Progress": "F",
    "Clear": "Failed"
  },
  {
    "UserID": "1192",
    "Nickname": "원빈",
    "Cool": "1483",
    "Good": "488",
    "Bad": "18",
    "Miss": "69",
    "MaxCombo": "394",
    "Acc": "2.1%",
    "Progress": "F",
    "Clear": "Failed"
  },
  {
    "UserID": "5621",
    "Nickname": "Deneb",
    "Cool": "1589",
    "Good": "354",
    "Bad": "21",
    "Miss": "75",
    "MaxCombo": "297",
    "Acc": "2.08%",
    "Progress": "F",
    "Clear": "Failed"
  },
  {
    "UserID": "5372",
    "Nickname": "사람임",
    "Cool": "1353",
    "Good": "306",
    "Bad": "29",
    "Miss": "63",
    "MaxCombo": "280",
    "Acc": "1.77%",
    "Progress": "F",
    "Clear": "Failed"
  },
  {
    "UserID": "5724",
    "Nickname": "번지",
    "Cool": "1170",
    "Good": "428",
    "Bad": "29",
    "Miss": "59",
    "MaxCombo": "296",
    "Acc": "1.71%",
    "Progress": "F",
    "Clear": "Failed"
  },
  {
    "UserID": "5632",
    "Nickname": "TT",
    "Cool": "1238",
    "Good": "358",
    "Bad": "10",
    "Miss": "63",
    "MaxCombo": "385",
    "Acc": "1.7%",
    "Progress": "F",
    "Clear": "Failed"
  },
  {
    "UserID": "5364",
    "Nickname": "페카",
    "Cool": "1238",
    "Good": "168",
    "Bad": "2",
    "Miss": "49",
    "MaxCombo": "456",
    "Acc": "1.5%",
    "Progress": "F",
    "Clear": "Failed"
  },
  {
    "UserID": "1223",
    "Nickname": "Sanni",
    "Cool": "871",
    "Good": "112",
    "Bad": "0",
    "Miss": "41",
    "MaxCombo": "386",
    "Acc": "1.05%",
    "Progress": "F",
    "Clear": "Failed"
  },
  {
    "UserID": "5959",
    "Nickname": "타다닥",
    "Cool": "547",
    "Good": "127",
    "Bad": "2",
    "Miss": "46",
    "MaxCombo": "123",
    "Acc": "0.72%",
    "Progress": "F",
    "Clear": "Failed"
  },
  {
    "UserID": "1195",
    "Nickname": "Destiny19",
    "Cool": "419",
    "Good": "105",
    "Bad": "3",
    "Miss": "39",
    "MaxCombo": "262",
    "Acc": "0.56%",
    "Progress": "F",
    "Clear": "Failed"
  },
  {
    "UserID": "6427",
    "Nickname": "woowang",
    "Cool": "329",
    "Good": "101",
    "Bad": "28",
    "Miss": "38",
    "MaxCombo": "75",
    "Acc": "0.46%",
    "Progress": "F",
    "Clear": "Failed"
  },
  {
    "UserID": "6052",
    "Nickname": "Wubby",
    "Cool": "327",
    "Good": "89",
    "Bad": "9",
    "Miss": "40",
    "MaxCombo": "134",
    "Acc": "0.44%",
    "Progress": "F",
    "Clear": "Failed"
  }
]