[
  {
    "UserID": "1166",
    "Nickname": "Delly.K",
    "Cool": "2924",
    "Good": "48",
    "Bad": "0",
    "Miss": "0",
    "MaxCombo": "2971",
    "Acc": "99.85%",
    "Progress": "SS",
    "Clear": "Clear"
  },
  {
    "UserID": "142",
    "Nickname": "SANDO",
    "Cool": "2910",
    "Good": "62",
    "Bad": "0",
    "Miss": "0",
    "MaxCombo": "2971",
    "Acc": "99.81%",
    "Progress": "SS",
    "Clear": "Clear"
  },
  {
    "UserID": "1183",
    "Nickname": "SacredReisen",
    "Cool": "2879",
    "Good": "93",
    "Bad": "0",
    "Miss": "0",
    "MaxCombo": "2971",
    "Acc": "99.72%",
    "Progress": "SS",
    "Clear": "Clear"
  },
  {
    "UserID": "152",
    "Nickname": "tomlee3",
    "Cool": "2934",
    "Good": "37",
    "Bad": "0",
    "Miss": "1",
    "MaxCombo": "2827",
    "Acc": "99.59%",
    "Progress": "SS",
    "Clear": "Clear"
  },
  {
    "UserID": "5501",
    "Nickname": "Angelina",
    "Cool": "2826",
    "Good": "142",
    "Bad": "0",
    "Miss": "4",
    "MaxCombo": "2059",
    "Acc": "98.36%",
    "Progress": "S",
    "Clear": "Clear"
  },
  {
    "UserID": "6229",
    "Nickname": "FenIndraWijaya",
    "Cool": "2894",
    "Good": "73",
    "Bad": "0",
    "Miss": "5",
    "MaxCombo": "1379",
    "Acc": "98.26%",
    "Progress": "S",
    "Clear": "Clear"
  },
  {
    "UserID": "1204",
    "Nickname": "거미",
    "Cool": "2774",
    "Good": "193",
    "Bad": "0",
    "Miss": "5",
    "MaxCombo": "1928",
    "Acc": "97.9%",
    "Progress": "S",
    "Clear": "Clear"
  },
  {
    "UserID": "6017",
    "Nickname": "SanniFanGirl",
    "Cool": "2878",
    "Good": "86",
    "Bad": "0",
    "Miss": "8",
    "MaxCombo": "1976",
    "Acc": "97.32%",
    "Progress": "S",
    "Clear": "Clear"
  },
  {
    "UserID": "1173",
    "Nickname": "SuperPlay",
    "Cool": "2356",
    "Good": "613",
    "Bad": "0",
    "Miss": "3",
    "MaxCombo": "1000",
    "Acc": "97.24%",
    "Progress": "S",
    "Clear": "Clear"
  },
  {
    "UserID": "6065",
    "Nickname": "LASvegas",
    "Cool": "2662",
    "Good": "303",
    "Bad": "1",
    "Miss": "6",
    "MaxCombo": "1273",
    "Acc": "96.96%",
    "Progress": "S",
    "Clear": "Clear"
  },
  {
    "UserID": "6025",
    "Nickname": "넨시",
    "Cool": "2524",
    "Good": "439",
    "Bad": "0",
    "Miss": "9",
    "MaxCombo": "1294",
    "Acc": "95.95%",
    "Progress": "A",
    "Clear": "Clear"
  },
  {
    "UserID": "5824",
    "Nickname": "딸기맛엄준식",
    "Cool": "2688",
    "Good": "269",
    "Bad": "0",
    "Miss": "15",
    "MaxCombo": "1122",
    "Acc": "94.64%",
    "Progress": "A",
    "Clear": "Clear"
  },
  {
    "UserID": "2309",
    "Nickname": "Yuel",
    "Cool": "2656",
    "Good": "301",
    "Bad": "0",
    "Miss": "15",
    "MaxCombo": "884",
    "Acc": "94.55%",
    "Progress": "A",
    "Clear": "Clear"
  },
  {
    "UserID": "4334",
    "Nickname": "zimcasts",
    "Cool": "2833",
    "Good": "122",
    "Bad": "2",
    "Miss": "15",
    "MaxCombo": "1229",
    "Acc": "94.48%",
    "Progress": "A",
    "Clear": "Clear"
  },
  {
    "UserID": "5365",
    "Nickname": "LaserMan",
    "Cool": "2761",
    "Good": "193",
    "Bad": "0",
    "Miss": "18",
    "MaxCombo": "740",
    "Acc": "93.96%",
    "Progress": "A",
    "Clear": "Clear"
  },
  {
    "UserID": "1191",
    "Nickname": "뉴비스",
    "Cool": "2756",
    "Good": "198",
    "Bad": "0",
    "Miss": "18",
    "MaxCombo": "912",
    "Acc": "93.95%",
    "Progress": "A",
    "Clear": "Clear"
  },
  {
    "UserID": "5728",
    "Nickname": "Tsnow",
    "Cool": "2722",
    "Good": "232",
    "Bad": "4",
    "Miss": "14",
    "MaxCombo": "1559",
    "Acc": "93.85%",
    "Progress": "A",
    "Clear": "Clear"
  },
  {
    "UserID": "5368",
    "Nickname": "햇살",
    "Cool": "2721",
    "Good": "233",
    "Bad": "2",
    "Miss": "16",
    "MaxCombo": "1241",
    "Acc": "93.84%",
    "Progress": "A",
    "Clear": "Clear"
  },
  {
    "UserID": "5377",
    "Nickname": "o2jaaamE",
    "Cool": "2672",
    "Good": "281",
    "Bad": "1",
    "Miss": "18",
    "MaxCombo": "968",
    "Acc": "93.4%",
    "Progress": "A",
    "Clear": "Clear"
  },
  {
    "UserID": "2257",
    "Nickname": "LunaticAnt",
    "Cool": "2758",
    "Good": "194",
    "Bad": "0",
    "Miss": "20",
    "MaxCombo": "814",
    "Acc": "93.36%",
    "Progress": "A",
    "Clear": "Clear"
  },
  {
    "UserID": "1207",
    "Nickname": "짬찌포병",
    "Cool": "2759",
    "Good": "192",
    "Bad": "0",
    "Miss": "21",
    "MaxCombo": "1296",
    "Acc": "93.06%",
    "Progress": "A",
    "Clear": "Clear"
  },
  {
    "UserID": "2",
    "Nickname": "김Ray",
    "Cool": "2719",
    "Good": "232",
    "Bad": "0",
    "Miss": "21",
    "MaxCombo": "1139",
    "Acc": "92.94%",
    "Progress": "A",
    "Clear": "Clear"
  },
  {
    "UserID": "2284",
    "Nickname": "Jance",
    "Cool": "2765",
    "Good": "184",
    "Bad": "0",
    "Miss": "23",
    "MaxCombo": "951",
    "Acc": "92.48%",
    "Progress": "A",
    "Clear": "Clear"
  },
  {
    "UserID": "4332",
    "Nickname": "mentor",
    "Cool": "2767",
    "Good": "181",
    "Bad": "0",
    "Miss": "24",
    "MaxCombo": "1160",
    "Acc": "92.18%",
    "Progress": "A",
    "Clear": "Clear"
  },
  {
    "UserID": "5359",
    "Nickname": "WaKa",
    "Cool": "2680",
    "Good": "268",
    "Bad": "6",
    "Miss": "18",
    "MaxCombo": "622",
    "Acc": "91.92%",
    "Progress": "A",
    "Clear": "Clear"
  },
  {
    "UserID": "6336",
    "Nickname": "머니",
    "Cool": "2654",
    "Good": "294",
    "Bad": "0",
    "Miss": "24",
    "MaxCombo": "631",
    "Acc": "91.84%",
    "Progress": "A",
    "Clear": "Clear"
  },
  {
    "UserID": "5600",
    "Nickname": "Nebula",
    "Cool": "2530",
    "Good": "419",
    "Bad": "0",
    "Miss": "23",
    "MaxCombo": "1132",
    "Acc": "91.77%",
    "Progress": "A",
    "Clear": "Clear"
  },
  {
    "UserID": "5428",
    "Nickname": "푸푸민우",
    "Cool": "2819",
    "Good": "127",
    "Bad": "3",
    "Miss": "23",
    "MaxCombo": "982",
    "Acc": "91.74%",
    "Progress": "A",
    "Clear": "Clear"
  },
  {
    "UserID": "5546",
    "Nickname": "allenkalbo",
    "Cool": "2862",
    "Good": "82",
    "Bad": "0",
    "Miss": "28",
    "MaxCombo": "1169",
    "Acc": "91.27%",
    "Progress": "A",
    "Clear": "Clear"
  },
  {
    "UserID": "72",
    "Nickname": "햇살",
    "Cool": "2757",
    "Good": "188",
    "Bad": "0",
    "Miss": "27",
    "MaxCombo": "755",
    "Acc": "91.25%",
    "Progress": "A",
    "Clear": "Clear"
  },
  {
    "UserID": "3335",
    "Nickname": "gero",
    "Cool": "2778",
    "Good": "165",
    "Bad": "0",
    "Miss": "29",
    "MaxCombo": "370",
    "Acc": "90.72%",
    "Progress": "A",
    "Clear": "Clear"
  },
  {
    "UserID": "2265",
    "Nickname": "제아롯드",
    "Cool": "2812",
    "Good": "129",
    "Bad": "0",
    "Miss": "31",
    "MaxCombo": "950",
    "Acc": "90.22%",
    "Progress": "A",
    "Clear": "Clear"
  },
  {
    "UserID": "3333",
    "Nickname": "kraiz19",
    "Cool": "2700",
    "Good": "240",
    "Bad": "4",
    "Miss": "28",
    "MaxCombo": "765",
    "Acc": "89.58%",
    "Progress": "B",
    "Clear": "Clear"
  },
  {
    "UserID": "5577",
    "Nickname": "Sweetsoul",
    "Cool": "2753",
    "Good": "186",
    "Bad": "1",
    "Miss": "32",
    "MaxCombo": "1437",
    "Acc": "89.44%",
    "Progress": "B",
    "Clear": "Clear"
  },
  {
    "UserID": "5431",
    "Nickname": "SSU",
    "Cool": "2576",
    "Good": "364",
    "Bad": "4",
    "Miss": "28",
    "MaxCombo": "835",
    "Acc": "89.21%",
    "Progress": "B",
    "Clear": "Clear"
  },
  {
    "UserID": "5445",
    "Nickname": "seolhari",
    "Cool": "2618",
    "Good": "321",
    "Bad": "2",
    "Miss": "31",
    "MaxCombo": "935",
    "Acc": "89.03%",
    "Progress": "B",
    "Clear": "Clear"
  },
  {
    "UserID": "2262",
    "Nickname": "Wizard",
    "Cool": "2615",
    "Good": "322",
    "Bad": "0",
    "Miss": "35",
    "MaxCombo": "914",
    "Acc": "88.43%",
    "Progress": "B",
    "Clear": "Clear"
  },
  {
    "UserID": "5620",
    "Nickname": "Niggy",
    "Cool": "2635",
    "Good": "300",
    "Bad": "2",
    "Miss": "35",
    "MaxCombo": "909",
    "Acc": "87.89%",
    "Progress": "B",
    "Clear": "Clear"
  },
  {
    "UserID": "5475",
    "Nickname": "shibatachun",
    "Cool": "2695",
    "Good": "236",
    "Bad": "1",
    "Miss": "40",
    "MaxCombo": "495",
    "Acc": "86.87%",
    "Progress": "B",
    "Clear": "Clear"
  },
  {
    "UserID": "1202",
    "Nickname": "뜌",
    "Cool": "2643",
    "Good": "288",
    "Bad": "3",
    "Miss": "38",
    "MaxCombo": "1332",
    "Acc": "86.71%",
    "Progress": "B",
    "Clear": "Clear"
  },
  {
    "UserID": "6370",
    "Nickname": "SeirenShikino",
    "Cool": "2618",
    "Good": "313",
    "Bad": "1",
    "Miss": "40",
    "MaxCombo": "1102",
    "Acc": "86.64%",
    "Progress": "B",
    "Clear": "Clear"
  },
  {
    "UserID": "5372",
    "Nickname": "사람임",
    "Cool": "2648",
    "Good": "282",
    "Bad": "3",
    "Miss": "39",
    "MaxCombo": "590",
    "Acc": "86.43%",
    "Progress": "B",
    "Clear": "Clear"
  },
  {
    "UserID": "5549",
    "Nickname": "windrush",
    "Cool": "2781",
    "Good": "147",
    "Bad": "0",
    "Miss": "44",
    "MaxCombo": "549",
    "Acc": "86.23%",
    "Progress": "B",
    "Clear": "Clear"
  },
  {
    "UserID": "1228",
    "Nickname": "11th",
    "Cool": "2666",
    "Good": "260",
    "Bad": "0",
    "Miss": "46",
    "MaxCombo": "568",
    "Acc": "85.28%",
    "Progress": "C",
    "Clear": "Clear"
  },
  {
    "UserID": "5438",
    "Nickname": "sssmeguminsss",
    "Cool": "2621",
    "Good": "304",
    "Bad": "0",
    "Miss": "47",
    "MaxCombo": "627",
    "Acc": "84.85%",
    "Progress": "C",
    "Clear": "Clear"
  },
  {
    "UserID": "5498",
    "Nickname": "kingxali",
    "Cool": "2685",
    "Good": "239",
    "Bad": "5",
    "Miss": "43",
    "MaxCombo": "530",
    "Acc": "84.74%",
    "Progress": "C",
    "Clear": "Clear"
  },
  {
    "UserID": "6149",
    "Nickname": "pado",
    "Cool": "2376",
    "Good": "551",
    "Bad": "9",
    "Miss": "36",
    "MaxCombo": "882",
    "Acc": "84.7%",
    "Progress": "C",
    "Clear": "Clear"
  },
  {
    "UserID": "5760",
    "Nickname": "invijoss",
    "Cool": "2492",
    "Good": "433",
    "Bad": "13",
    "Miss": "34",
    "MaxCombo": "368",
    "Acc": "84.46%",
    "Progress": "C",
    "Clear": "Clear"
  },
  {
    "UserID": "2263",
    "Nickname": "Eve",
    "Cool": "2506",
    "Good": "417",
    "Bad": "8",
    "Miss": "41",
    "MaxCombo": "766",
    "Acc": "83.9%",
    "Progress": "C",
    "Clear": "Clear"
  },
  {
    "UserID": "5407",
    "Nickname": "안다로미",
    "Cool": "2674",
    "Good": "245",
    "Bad": "4",
    "Miss": "49",
    "MaxCombo": "750",
    "Acc": "83.21%",
    "Progress": "C",
    "Clear": "Clear"
  },
  {
    "UserID": "4338",
    "Nickname": "CratyII",
    "Cool": "2428",
    "Good": "493",
    "Bad": "0",
    "Miss": "51",
    "MaxCombo": "896",
    "Acc": "83.06%",
    "Progress": "C",
    "Clear": "Clear"
  },
  {
    "UserID": "2272",
    "Nickname": "skswkd",
    "Cool": "2567",
    "Good": "352",
    "Bad": "8",
    "Miss": "45",
    "MaxCombo": "494",
    "Acc": "82.88%",
    "Progress": "C",
    "Clear": "Clear"
  },
  {
    "UserID": "2304",
    "Nickname": "Asta`Kun",
    "Cool": "1646",
    "Good": "1282",
    "Bad": "11",
    "Miss": "33",
    "MaxCombo": "485",
    "Acc": "82.79%",
    "Progress": "C",
    "Clear": "Clear"
  },
  {
    "UserID": "5968",
    "Nickname": "adas",
    "Cool": "2676",
    "Good": "239",
    "Bad": "1",
    "Miss": "56",
    "MaxCombo": "433",
    "Acc": "82.02%",
    "Progress": "C",
    "Clear": "Clear"
  },
  {
    "UserID": "2330",
    "Nickname": "Looon",
    "Cool": "2683",
    "Good": "231",
    "Bad": "10",
    "Miss": "48",
    "MaxCombo": "744",
    "Acc": "81.74%",
    "Progress": "C",
    "Clear": "Clear"
  },
  {
    "UserID": "6016",
    "Nickname": "aid",
    "Cool": "2704",
    "Good": "209",
    "Bad": "4",
    "Miss": "55",
    "MaxCombo": "540",
    "Acc": "81.5%",
    "Progress": "C",
    "Clear": "Clear"
  },
  {
    "UserID": "4347",
    "Nickname": "hekqb77777",
    "Cool": "2543",
    "Good": "371",
    "Bad": "2",
    "Miss": "56",
    "MaxCombo": "963",
    "Acc": "81.31%",
    "Progress": "C",
    "Clear": "Clear"
  },
  {
    "UserID": "5621",
    "Nickname": "Deneb",
    "Cool": "2705",
    "Good": "206",
    "Bad": "6",
    "Miss": "55",
    "MaxCombo": "607",
    "Acc": "80.9%",
    "Progress": "C",
    "Clear": "Clear"
  },
  {
    "UserID": "5883",
    "Nickname": "Yiku",
    "Cool": "2519",
    "Good": "393",
    "Bad": "10",
    "Miss": "50",
    "MaxCombo": "1250",
    "Acc": "80.64%",
    "Progress": "C",
    "Clear": "Clear"
  },
  {
    "UserID": "2324",
    "Nickname": "FullOptions",
    "Cool": "2578",
    "Good": "332",
    "Bad": "8",
    "Miss": "54",
    "MaxCombo": "756",
    "Acc": "80.22%",
    "Progress": "C",
    "Clear": "Clear"
  },
  {
    "UserID": "6452",
    "Nickname": "Ayam88",
    "Cool": "2424",
    "Good": "487",
    "Bad": "6",
    "Miss": "55",
    "MaxCombo": "750",
    "Acc": "80.05%",
    "Progress": "C",
    "Clear": "Clear"
  },
  {
    "UserID": "1192",
    "Nickname": "원빈",
    "Cool": "2256",
    "Good": "655",
    "Bad": "23",
    "Miss": "38",
    "MaxCombo": "1113",
    "Acc": "79.54%",
    "Progress": "C",
    "Clear": "Clear"
  },
  {
    "UserID": "5740",
    "Nickname": "DOG10DUK",
    "Cool": "2545",
    "Good": "362",
    "Bad": "13",
    "Miss": "52",
    "MaxCombo": "540",
    "Acc": "79.22%",
    "Progress": "C",
    "Clear": "Clear"
  },
  {
    "UserID": "3334",
    "Nickname": "Gamer97",
    "Cool": "2600",
    "Good": "306",
    "Bad": "4",
    "Miss": "62",
    "MaxCombo": "741",
    "Acc": "79.09%",
    "Progress": "C",
    "Clear": "Clear"
  },
  {
    "UserID": "5394",
    "Nickname": "Cypher",
    "Cool": "2482",
    "Good": "425",
    "Bad": "10",
    "Miss": "55",
    "MaxCombo": "591",
    "Acc": "79.03%",
    "Progress": "C",
    "Clear": "Clear"
  },
  {
    "UserID": "5594",
    "Nickname": "예승이콩",
    "Cool": "2635",
    "Good": "270",
    "Bad": "0",
    "Miss": "67",
    "MaxCombo": "243",
    "Acc": "78.89%",
    "Progress": "C",
    "Clear": "Clear"
  },
  {
    "UserID": "6052",
    "Nickname": "Wubby",
    "Cool": "2403",
    "Good": "504",
    "Bad": "16",
    "Miss": "49",
    "MaxCombo": "624",
    "Acc": "78.79%",
    "Progress": "C",
    "Clear": "Clear"
  },
  {
    "UserID": "5446",
    "Nickname": "ChnXiaoXu",
    "Cool": "2462",
    "Good": "443",
    "Bad": "13",
    "Miss": "54",
    "MaxCombo": "614",
    "Acc": "78.37%",
    "Progress": "C",
    "Clear": "Clear"
  },
  {
    "UserID": "6341",
    "Nickname": "Hyojin",
    "Cool": "2557",
    "Good": "346",
    "Bad": "9",
    "Miss": "60",
    "MaxCombo": "541",
    "Acc": "78.06%",
    "Progress": "C",
    "Clear": "Clear"
  },
  {
    "UserID": "5928",
    "Nickname": "밤이",
    "Cool": "2509",
    "Good": "392",
    "Bad": "10",
    "Miss": "61",
    "MaxCombo": "791",
    "Acc": "77.31%",
    "Progress": "D",
    "Clear": "Clear"
  },
  {
    "UserID": "6053",
    "Nickname": "FakeException",
    "Cool": "2713",
    "Good": "185",
    "Bad": "13",
    "Miss": "61",
    "MaxCombo": "483",
    "Acc": "77.03%",
    "Progress": "D",
    "Clear": "Clear"
  },
  {
    "UserID": "5965",
    "Nickname": "AnattA",
    "Cool": "2588",
    "Good": "311",
    "Bad": "3",
    "Miss": "70",
    "MaxCombo": "609",
    "Acc": "76.95%",
    "Progress": "D",
    "Clear": "Clear"
  },
  {
    "UserID": "5447",
    "Nickname": "노스",
    "Cool": "2550",
    "Good": "348",
    "Bad": "1",
    "Miss": "73",
    "MaxCombo": "584",
    "Acc": "76.54%",
    "Progress": "D",
    "Clear": "Clear"
  },
  {
    "UserID": "5392",
    "Nickname": "LuckyAA",
    "Cool": "2441",
    "Good": "458",
    "Bad": "11",
    "Miss": "62",
    "MaxCombo": "944",
    "Acc": "76.51%",
    "Progress": "D",
    "Clear": "Clear"
  },
  {
    "UserID": "5658",
    "Nickname": "Sizilien",
    "Cool": "2419",
    "Good": "479",
    "Bad": "13",
    "Miss": "61",
    "MaxCombo": "385",
    "Acc": "76.14%",
    "Progress": "D",
    "Clear": "Clear"
  },
  {
    "UserID": "6093",
    "Nickname": "Kenth",
    "Cool": "2354",
    "Good": "544",
    "Bad": "9",
    "Miss": "65",
    "MaxCombo": "592",
    "Acc": "75.94%",
    "Progress": "D",
    "Clear": "Clear"
  },
  {
    "UserID": "6459",
    "Nickname": "박호두로스컷",
    "Cool": "2143",
    "Good": "757",
    "Bad": "9",
    "Miss": "63",
    "MaxCombo": "962",
    "Acc": "75.9%",
    "Progress": "D",
    "Clear": "Clear"
  },
  {
    "UserID": "5768",
    "Nickname": "CoffeeMix",
    "Cool": "2535",
    "Good": "360",
    "Bad": "0",
    "Miss": "77",
    "MaxCombo": "509",
    "Acc": "75.59%",
    "Progress": "D",
    "Clear": "Clear"
  },
  {
    "UserID": "5640",
    "Nickname": "nohii",
    "Cool": "2109",
    "Good": "790",
    "Bad": "21",
    "Miss": "52",
    "MaxCombo": "1057",
    "Acc": "75.5%",
    "Progress": "D",
    "Clear": "Clear"
  },
  {
    "UserID": "2269",
    "Nickname": "Peyn",
    "Cool": "2438",
    "Good": "457",
    "Bad": "5",
    "Miss": "72",
    "MaxCombo": "339",
    "Acc": "75.3%",
    "Progress": "D",
    "Clear": "Clear"
  },
  {
    "UserID": "5398",
    "Nickname": "Sariel",
    "Cool": "2583",
    "Good": "310",
    "Bad": "8",
    "Miss": "71",
    "MaxCombo": "637",
    "Acc": "75.14%",
    "Progress": "D",
    "Clear": "Clear"
  },
  {
    "UserID": "6008",
    "Nickname": "Guodan",
    "Cool": "2463",
    "Good": "430",
    "Bad": "17",
    "Miss": "62",
    "MaxCombo": "1106",
    "Acc": "74.77%",
    "Progress": "D",
    "Clear": "Clear"
  },
  {
    "UserID": "1188",
    "Nickname": "Cuppp",
    "Cool": "2292",
    "Good": "602",
    "Bad": "20",
    "Miss": "58",
    "MaxCombo": "589",
    "Acc": "74.56%",
    "Progress": "D",
    "Clear": "Clear"
  },
  {
    "UserID": "2276",
    "Nickname": "bsc0626",
    "Cool": "2486",
    "Good": "404",
    "Bad": "8",
    "Miss": "74",
    "MaxCombo": "349",
    "Acc": "73.94%",
    "Progress": "D",
    "Clear": "Clear"
  },
  {
    "UserID": "5735",
    "Nickname": "shaafs",
    "Cool": "2359",
    "Good": "531",
    "Bad": "6",
    "Miss": "76",
    "MaxCombo": "1108",
    "Acc": "73.56%",
    "Progress": "D",
    "Clear": "Clear"
  },
  {
    "UserID": "6438",
    "Nickname": "Jor",
    "Cool": "2567",
    "Good": "320",
    "Bad": "18",
    "Miss": "67",
    "MaxCombo": "421",
    "Acc": "73.29%",
    "Progress": "D",
    "Clear": "Clear"
  },
  {
    "UserID": "5745",
    "Nickname": "Alexiel",
    "Cool": "2449",
    "Good": "438",
    "Bad": "11",
    "Miss": "74",
    "MaxCombo": "574",
    "Acc": "72.93%",
    "Progress": "D",
    "Clear": "Clear"
  },
  {
    "UserID": "4348",
    "Nickname": "nadavv",
    "Cool": "2310",
    "Good": "578",
    "Bad": "22",
    "Miss": "62",
    "MaxCombo": "300",
    "Acc": "72.81%",
    "Progress": "D",
    "Clear": "Clear"
  },
  {
    "UserID": "6242",
    "Nickname": "Jfritz",
    "Cool": "2291",
    "Good": "597",
    "Bad": "21",
    "Miss": "63",
    "MaxCombo": "780",
    "Acc": "72.75%",
    "Progress": "D",
    "Clear": "Clear"
  },
  {
    "UserID": "5362",
    "Nickname": "unique",
    "Cool": "1912",
    "Good": "979",
    "Bad": "17",
    "Miss": "64",
    "MaxCombo": "1197",
    "Acc": "72.51%",
    "Progress": "D",
    "Clear": "Clear"
  },
  {
    "UserID": "5373",
    "Nickname": "곽청아",
    "Cool": "2651",
    "Good": "232",
    "Bad": "20",
    "Miss": "69",
    "MaxCombo": "479",
    "Acc": "72.35%",
    "Progress": "D",
    "Clear": "Clear"
  },
  {
    "UserID": "5352",
    "Nickname": "Ravile",
    "Cool": "2160",
    "Good": "726",
    "Bad": "1",
    "Miss": "85",
    "MaxCombo": "591",
    "Acc": "71.76%",
    "Progress": "D",
    "Clear": "Clear"
  },
  {
    "UserID": "94",
    "Nickname": "오노",
    "Cool": "2118",
    "Good": "768",
    "Bad": "8",
    "Miss": "78",
    "MaxCombo": "466",
    "Acc": "71.63%",
    "Progress": "D",
    "Clear": "Clear"
  },
  {
    "UserID": "5780",
    "Nickname": "ririri",
    "Cool": "2385",
    "Good": "498",
    "Bad": "8",
    "Miss": "81",
    "MaxCombo": "585",
    "Acc": "71.54%",
    "Progress": "D",
    "Clear": "Clear"
  },
  {
    "UserID": "5897",
    "Nickname": "베키",
    "Cool": "2489",
    "Good": "389",
    "Bad": "14",
    "Miss": "80",
    "MaxCombo": "317",
    "Acc": "70.36%",
    "Progress": "D",
    "Clear": "Clear"
  },
  {
    "UserID": "5961",
    "Nickname": "lsh0222",
    "Cool": "2530",
    "Good": "342",
    "Bad": "19",
    "Miss": "81",
    "MaxCombo": "450",
    "Acc": "68.68%",
    "Progress": "D",
    "Clear": "Clear"
  },
  {
    "UserID": "5724",
    "Nickname": "번지",
    "Cool": "2030",
    "Good": "847",
    "Bad": "26",
    "Miss": "69",
    "MaxCombo": "577",
    "Acc": "68.67%",
    "Progress": "D",
    "Clear": "Clear"
  },
  {
    "UserID": "5508",
    "Nickname": "pob",
    "Cool": "2280",
    "Good": "588",
    "Bad": "17",
    "Miss": "87",
    "MaxCombo": "480",
    "Acc": "66.73%",
    "Progress": "D",
    "Clear": "Clear"
  },
  {
    "UserID": "5581",
    "Nickname": "Harvest",
    "Cool": "2527",
    "Good": "335",
    "Bad": "21",
    "Miss": "89",
    "MaxCombo": "270",
    "Acc": "65.67%",
    "Progress": "D",
    "Clear": "Clear"
  },
  {
    "UserID": "5361",
    "Nickname": "2Coma",
    "Cool": "2509",
    "Good": "352",
    "Bad": "26",
    "Miss": "85",
    "MaxCombo": "320",
    "Acc": "65.32%",
    "Progress": "D",
    "Clear": "Clear"
  },
  {
    "UserID": "6080",
    "Nickname": "Mmg",
    "Cool": "2316",
    "Good": "539",
    "Bad": "25",
    "Miss": "92",
    "MaxCombo": "287",
    "Acc": "62.94%",
    "Progress": "D",
    "Clear": "Clear"
  },
  {
    "UserID": "5496",
    "Nickname": "namae",
    "Cool": "2381",
    "Good": "472",
    "Bad": "24",
    "Miss": "95",
    "MaxCombo": "459",
    "Acc": "62.53%",
    "Progress": "D",
    "Clear": "Clear"
  },
  {
    "UserID": "5524",
    "Nickname": "kyg3478",
    "Cool": "2104",
    "Good": "739",
    "Bad": "46",
    "Miss": "83",
    "MaxCombo": "437",
    "Acc": "58.7%",
    "Progress": "D",
    "Clear": "Clear"
  },
  {
    "UserID": "6313",
    "Nickname": "Jich",
    "Cool": "2285",
    "Good": "510",
    "Bad": "15",
    "Miss": "92",
    "MaxCombo": "378",
    "Acc": "35.88%",
    "Progress": "F",
    "Clear": "Failed"
  },
  {
    "UserID": "5842",
    "Nickname": "Severity",
    "Cool": "2272",
    "Good": "449",
    "Bad": "20",
    "Miss": "78",
    "MaxCombo": "562",
    "Acc": "18.1%",
    "Progress": "F",
    "Clear": "Failed"
  },
  {
    "UserID": "5628",
    "Nickname": "mgas",
    "Cool": "2095",
    "Good": "627",
    "Bad": "13",
    "Miss": "85",
    "MaxCombo": "324",
    "Acc": "17.92%",
    "Progress": "F",
    "Clear": "Failed"
  },
  {
    "UserID": "5822",
    "Nickname": "실존하는허수",
    "Cool": "2203",
    "Good": "283",
    "Bad": "5",
    "Miss": "85",
    "MaxCombo": "560",
    "Acc": "9.28%",
    "Progress": "F",
    "Clear": "Failed"
  },
  {
    "UserID": "6137",
    "Nickname": "truyenvu",
    "Cool": "2088",
    "Good": "595",
    "Bad": "31",
    "Miss": "75",
    "MaxCombo": "576",
    "Acc": "8.54%",
    "Progress": "F",
    "Clear": "Failed"
  },
  {
    "UserID": "6230",
    "Nickname": "JRTRECE",
    "Cool": "2322",
    "Good": "325",
    "Bad": "9",
    "Miss": "64",
    "MaxCombo": "1143",
    "Acc": "7.91%",
    "Progress": "F",
    "Clear": "Failed"
  },
  {
    "UserID": "3328",
    "Nickname": "Ran",
    "Cool": "2111",
    "Good": "526",
    "Bad": "27",
    "Miss": "89",
    "MaxCombo": "376",
    "Acc": "7.87%",
    "Progress": "F",
    "Clear": "Failed"
  },
  {
    "UserID": "5944",
    "Nickname": "XaouXaou",
    "Cool": "2164",
    "Good": "470",
    "Bad": "10",
    "Miss": "88",
    "MaxCombo": "299",
    "Acc": "7.86%",
    "Progress": "F",
    "Clear": "Failed"
  },
  {
    "UserID": "5814",
    "Nickname": "Enoku",
    "Cool": "2162",
    "Good": "471",
    "Bad": "42",
    "Miss": "80",
    "MaxCombo": "645",
    "Acc": "7.86%",
    "Progress": "F",
    "Clear": "Failed"
  },
  {
    "UserID": "165",
    "Nickname": "Chess",
    "Cool": "2274",
    "Good": "314",
    "Bad": "36",
    "Miss": "61",
    "MaxCombo": "412",
    "Acc": "7.73%",
    "Progress": "F",
    "Clear": "Failed"
  },
  {
    "UserID": "5956",
    "Nickname": "coro",
    "Cool": "2230",
    "Good": "338",
    "Bad": "7",
    "Miss": "89",
    "MaxCombo": "474",
    "Acc": "7.67%",
    "Progress": "F",
    "Clear": "Failed"
  },
  {
    "UserID": "1174",
    "Nickname": "GUMI",
    "Cool": "2130",
    "Good": "424",
    "Bad": "14",
    "Miss": "86",
    "MaxCombo": "566",
    "Acc": "7.63%",
    "Progress": "F",
    "Clear": "Failed"
  },
  {
    "UserID": "5813",
    "Nickname": "스알",
    "Cool": "2311",
    "Good": "232",
    "Bad": "1",
    "Miss": "47",
    "MaxCombo": "1042",
    "Acc": "7.6%",
    "Progress": "F",
    "Clear": "Failed"
  },
  {
    "UserID": "3327",
    "Nickname": "WNCC",
    "Cool": "2199",
    "Good": "342",
    "Bad": "8",
    "Miss": "77",
    "MaxCombo": "590",
    "Acc": "7.59%",
    "Progress": "F",
    "Clear": "Failed"
  },
  {
    "UserID": "6036",
    "Nickname": "Van27",
    "Cool": "1957",
    "Good": "579",
    "Bad": "37",
    "Miss": "80",
    "MaxCombo": "284",
    "Acc": "7.57%",
    "Progress": "F",
    "Clear": "Failed"
  },
  {
    "UserID": "5766",
    "Nickname": "Irish",
    "Cool": "1982",
    "Good": "523",
    "Bad": "19",
    "Miss": "83",
    "MaxCombo": "238",
    "Acc": "7.48%",
    "Progress": "F",
    "Clear": "Failed"
  },
  {
    "UserID": "5483",
    "Nickname": "Sirelia",
    "Cool": "1939",
    "Good": "431",
    "Bad": "19",
    "Miss": "88",
    "MaxCombo": "353",
    "Acc": "7.08%",
    "Progress": "F",
    "Clear": "Failed"
  },
  {
    "UserID": "5844",
    "Nickname": "Seroto",
    "Cool": "1864",
    "Good": "454",
    "Bad": "31",
    "Miss": "84",
    "MaxCombo": "407",
    "Acc": "6.92%",
    "Progress": "F",
    "Clear": "Failed"
  },
  {
    "UserID": "5468",
    "Nickname": "choichan",
    "Cool": "1937",
    "Good": "259",
    "Bad": "25",
    "Miss": "86",
    "MaxCombo": "196",
    "Acc": "6.56%",
    "Progress": "F",
    "Clear": "Failed"
  },
  {
    "UserID": "5358",
    "Nickname": "Cyubic",
    "Cool": "1883",
    "Good": "269",
    "Bad": "1",
    "Miss": "47",
    "MaxCombo": "967",
    "Acc": "6.43%",
    "Progress": "F",
    "Clear": "Failed"
  },
  {
    "UserID": "5718",
    "Nickname": "Stacy",
    "Cool": "975",
    "Good": "463",
    "Bad": "13",
    "Miss": "51",
    "MaxCombo": "283",
    "Acc": "4.29%",
    "Progress": "F",
    "Clear": "Failed"
  },
  {
    "UserID": "5582",
    "Nickname": "궁상",
    "Cool": "1021",
    "Good": "217",
    "Bad": "11",
    "Miss": "58",
    "MaxCombo": "195",
    "Acc": "3.7%",
    "Progress": "F",
    "Clear": "Failed"
  },
  {
    "UserID": "5721",
    "Nickname": "Ellysown",
    "Cool": "886",
    "Good": "264",
    "Bad": "9",
    "Miss": "55",
    "MaxCombo": "123",
    "Acc": "3.43%",
    "Progress": "F",
    "Clear": "Failed"
  },
  {
    "UserID": "6389",
    "Nickname": "Aihara",
    "Cool": "943",
    "Good": "60",
    "Bad": "0",
    "Miss": "38",
    "MaxCombo": "638",
    "Acc": "3.0%",
    "Progress": "F",
    "Clear": "Failed"
  },
  {
    "UserID": "5875",
    "Nickname": "툰툰",
    "Cool": "787",
    "Good": "213",
    "Bad": "7",
    "Miss": "48",
    "MaxCombo": "176",
    "Acc": "2.98%",
    "Progress": "F",
    "Clear": "Failed"
  },
  {
    "UserID": "6134",
    "Nickname": "거북이날개",
    "Cool": "797",
    "Good": "201",
    "Bad": "7",
    "Miss": "53",
    "MaxCombo": "153",
    "Acc": "2.98%",
    "Progress": "F",
    "Clear": "Failed"
  },
  {
    "UserID": "5622",
    "Nickname": "레나",
    "Cool": "928",
    "Good": "67",
    "Bad": "0",
    "Miss": "41",
    "MaxCombo": "384",
    "Acc": "2.97%",
    "Progress": "F",
    "Clear": "Failed"
  },
  {
    "UserID": "4344",
    "Nickname": "Zola",
    "Cool": "728",
    "Good": "269",
    "Bad": "23",
    "Miss": "47",
    "MaxCombo": "154",
    "Acc": "2.97%",
    "Progress": "F",
    "Clear": "Failed"
  },
  {
    "UserID": "5907",
    "Nickname": "Holycoldwater",
    "Cool": "811",
    "Good": "183",
    "Bad": "11",
    "Miss": "52",
    "MaxCombo": "222",
    "Acc": "2.97%",
    "Progress": "F",
    "Clear": "Failed"
  },
  {
    "UserID": "5385",
    "Nickname": "TulFak",
    "Cool": "876",
    "Good": "115",
    "Bad": "5",
    "Miss": "48",
    "MaxCombo": "258",
    "Acc": "2.96%",
    "Progress": "F",
    "Clear": "Failed"
  },
  {
    "UserID": "5360",
    "Nickname": "asdfunknown",
    "Cool": "842",
    "Good": "146",
    "Bad": "6",
    "Miss": "44",
    "MaxCombo": "301",
    "Acc": "2.95%",
    "Progress": "F",
    "Clear": "Failed"
  },
  {
    "UserID": "6245",
    "Nickname": "yuuki",
    "Cool": "797",
    "Good": "191",
    "Bad": "4",
    "Miss": "45",
    "MaxCombo": "233",
    "Acc": "2.95%",
    "Progress": "F",
    "Clear": "Failed"
  },
  {
    "UserID": "5547",
    "Nickname": "Stug",
    "Cool": "775",
    "Good": "211",
    "Bad": "8",
    "Miss": "41",
    "MaxCombo": "278",
    "Acc": "2.94%",
    "Progress": "F",
    "Clear": "Failed"
  },
  {
    "UserID": "5931",
    "Nickname": "Xyphoes",
    "Cool": "667",
    "Good": "317",
    "Bad": "16",
    "Miss": "50",
    "MaxCombo": "165",
    "Acc": "2.93%",
    "Progress": "F",
    "Clear": "Failed"
  },
  {
    "UserID": "6284",
    "Nickname": "dyboiced",
    "Cool": "841",
    "Good": "138",
    "Bad": "2",
    "Miss": "49",
    "MaxCombo": "240",
    "Acc": "2.92%",
    "Progress": "F",
    "Clear": "Failed"
  },
  {
    "UserID": "6150",
    "Nickname": "피엘",
    "Cool": "804",
    "Good": "169",
    "Bad": "1",
    "Miss": "57",
    "MaxCombo": "130",
    "Acc": "2.9%",
    "Progress": "F",
    "Clear": "Failed"
  },
  {
    "UserID": "4326",
    "Nickname": "BananenTropfen",
    "Cool": "798",
    "Good": "172",
    "Bad": "20",
    "Miss": "45",
    "MaxCombo": "315",
    "Acc": "2.9%",
    "Progress": "F",
    "Clear": "Failed"
  },
  {
    "UserID": "6254",
    "Nickname": "CurlJam",
    "Cool": "878",
    "Good": "91",
    "Bad": "0",
    "Miss": "49",
    "MaxCombo": "380",
    "Acc": "2.9%",
    "Progress": "F",
    "Clear": "Failed"
  },
  {
    "UserID": "5639",
    "Nickname": "ac99",
    "Cool": "854",
    "Good": "107",
    "Bad": "16",
    "Miss": "55",
    "MaxCombo": "148",
    "Acc": "2.87%",
    "Progress": "F",
    "Clear": "Failed"
  },
  {
    "UserID": "5684",
    "Nickname": "Lilith",
    "Cool": "669",
    "Good": "290",
    "Bad": "10",
    "Miss": "45",
    "MaxCombo": "236",
    "Acc": "2.86%",
    "Progress": "F",
    "Clear": "Failed"
  },
  {
    "UserID": "6113",
    "Nickname": "Hope",
    "Cool": "829",
    "Good": "126",
    "Bad": "4",
    "Miss": "55",
    "MaxCombo": "222",
    "Acc": "2.85%",
    "Progress": "F",
    "Clear": "Failed"
  },
  {
    "UserID": "5923",
    "Nickname": "uwuLUNAuwu",
    "Cool": "708",
    "Good": "248",
    "Bad": "21",
    "Miss": "43",
    "MaxCombo": "241",
    "Acc": "2.85%",
    "Progress": "F",
    "Clear": "Failed"
  },
  {
    "UserID": "5671",
    "Nickname": "Olrock",
    "Cool": "770",
    "Good": "181",
    "Bad": "15",
    "Miss": "50",
    "MaxCombo": "244",
    "Acc": "2.84%",
    "Progress": "F",
    "Clear": "Failed"
  },
  {
    "UserID": "3326",
    "Nickname": "Zeevee",
    "Cool": "715",
    "Good": "232",
    "Bad": "3",
    "Miss": "46",
    "MaxCombo": "200",
    "Acc": "2.83%",
    "Progress": "F",
    "Clear": "Failed"
  },
  {
    "UserID": "5543",
    "Nickname": "feesh",
    "Cool": "615",
    "Good": "324",
    "Bad": "6",
    "Miss": "48",
    "MaxCombo": "154",
    "Acc": "2.8%",
    "Progress": "F",
    "Clear": "Failed"
  },
  {
    "UserID": "6359",
    "Nickname": "Hentu",
    "Cool": "711",
    "Good": "227",
    "Bad": "0",
    "Miss": "53",
    "MaxCombo": "150",
    "Acc": "2.8%",
    "Progress": "F",
    "Clear": "Failed"
  },
  {
    "UserID": "6417",
    "Nickname": "Poniria",
    "Cool": "745",
    "Good": "160",
    "Bad": "4",
    "Miss": "44",
    "MaxCombo": "203",
    "Acc": "2.7%",
    "Progress": "F",
    "Clear": "Failed"
  },
  {
    "UserID": "6296",
    "Nickname": "Yume",
    "Cool": "538",
    "Good": "330",
    "Bad": "24",
    "Miss": "44",
    "MaxCombo": "150",
    "Acc": "2.59%",
    "Progress": "F",
    "Clear": "Failed"
  },
  {
    "UserID": "6427",
    "Nickname": "woowang",
    "Cool": "561",
    "Good": "164",
    "Bad": "21",
    "Miss": "47",
    "MaxCombo": "63",
    "Acc": "2.16%",
    "Progress": "F",
    "Clear": "Failed"
  },
  {
    "UserID": "6381",
    "Nickname": "Kuroda",
    "Cool": "496",
    "Good": "207",
    "Bad": "36",
    "Miss": "38",
    "MaxCombo": "232",
    "Acc": "2.1%",
    "Progress": "F",
    "Clear": "Failed"
  },
  {
    "UserID": "6402",
    "Nickname": "Naurel",
    "Cool": "289",
    "Good": "21",
    "Bad": "0",
    "Miss": "36",
    "MaxCombo": "200",
    "Acc": "0.93%",
    "Progress": "F",
    "Clear": "Failed"
  }
]