[
  {
    "UserID": "1168",
    "Nickname": "자드",
    "Cool": "4736",
    "Good": "1455",
    "Bad": "21",
    "Miss": "144",
    "MaxCombo": "641",
    "Acc": "74.58%",
    "Progress": "D",
    "Clear": "Clear"
  },
  {
    "UserID": "80",
    "Nickname": "쵸익",
    "Cool": "4569",
    "Good": "1619",
    "Bad": "34",
    "Miss": "134",
    "MaxCombo": "383",
    "Acc": "73.92%",
    "Progress": "D",
    "Clear": "Clear"
  },
  {
    "UserID": "72",
    "Nickname": "햇살",
    "Cool": "2853",
    "Good": "1645",
    "Bad": "35",
    "Miss": "110",
    "MaxCombo": "646",
    "Acc": "6.27%",
    "Progress": "F",
    "Clear": "Failed"
  },
  {
    "UserID": "136",
    "Nickname": "시각",
    "Cool": "2891",
    "Good": "803",
    "Bad": "8",
    "Miss": "97",
    "MaxCombo": "328",
    "Acc": "5.15%",
    "Progress": "F",
    "Clear": "Failed"
  },
  {
    "UserID": "1169",
    "Nickname": "Nori",
    "Cool": "2682",
    "Good": "974",
    "Bad": "45",
    "Miss": "87",
    "MaxCombo": "712",
    "Acc": "5.1%",
    "Progress": "F",
    "Clear": "Failed"
  },
  {
    "UserID": "1166",
    "Nickname": "Delly.K",
    "Cool": "1966",
    "Good": "743",
    "Bad": "16",
    "Miss": "85",
    "MaxCombo": "266",
    "Acc": "3.78%",
    "Progress": "F",
    "Clear": "Failed"
  },
  {
    "UserID": "2260",
    "Nickname": "짜이우",
    "Cool": "1787",
    "Good": "391",
    "Bad": "27",
    "Miss": "64",
    "MaxCombo": "508",
    "Acc": "3.04%",
    "Progress": "F",
    "Clear": "Failed"
  },
  {
    "UserID": "5408",
    "Nickname": "LCnanoda",
    "Cool": "1620",
    "Good": "508",
    "Bad": "22",
    "Miss": "73",
    "MaxCombo": "306",
    "Acc": "2.97%",
    "Progress": "F",
    "Clear": "Failed"
  },
  {
    "UserID": "5626",
    "Nickname": "anti",
    "Cool": "1676",
    "Good": "341",
    "Bad": "31",
    "Miss": "78",
    "MaxCombo": "377",
    "Acc": "2.82%",
    "Progress": "F",
    "Clear": "Failed"
  },
  {
    "UserID": "148",
    "Nickname": "뽕",
    "Cool": "1356",
    "Good": "586",
    "Bad": "2",
    "Miss": "63",
    "MaxCombo": "382",
    "Acc": "2.71%",
    "Progress": "F",
    "Clear": "Failed"
  },
  {
    "UserID": "139",
    "Nickname": "아크네스",
    "Cool": "1193",
    "Good": "480",
    "Bad": "14",
    "Miss": "65",
    "MaxCombo": "294",
    "Acc": "2.33%",
    "Progress": "F",
    "Clear": "Failed"
  },
  {
    "UserID": "1195",
    "Nickname": "Destiny19",
    "Cool": "1045",
    "Good": "411",
    "Bad": "17",
    "Miss": "63",
    "MaxCombo": "257",
    "Acc": "2.03%",
    "Progress": "F",
    "Clear": "Failed"
  },
  {
    "UserID": "5390",
    "Nickname": "Myzki",
    "Cool": "840",
    "Good": "284",
    "Bad": "18",
    "Miss": "52",
    "MaxCombo": "203",
    "Acc": "1.57%",
    "Progress": "F",
    "Clear": "Failed"
  },
  {
    "UserID": "3327",
    "Nickname": "WNCC",
    "Cool": "208",
    "Good": "167",
    "Bad": "25",
    "Miss": "34",
    "MaxCombo": "134",
    "Acc": "0.52%",
    "Progress": "F",
    "Clear": "Failed"
  },
  {
    "UserID": "2324",
    "Nickname": "FullOptions",
    "Cool": "238",
    "Good": "127",
    "Bad": "13",
    "Miss": "36",
    "MaxCombo": "119",
    "Acc": "0.51%",
    "Progress": "F",
    "Clear": "Failed"
  }
]