[
  {
    "UserID": "1168",
    "Nickname": "자드",
    "Cool": "4347",
    "Good": "1310",
    "Bad": "2",
    "Miss": "17",
    "MaxCombo": "2470",
    "Acc": "94.91%",
    "Progress": "A Rank",
    "Clear": "Cleared",
    "PlayTime": "2022-06-13 21:34:02"
  },
  {
    "UserID": "80",
    "Nickname": "쵸익",
    "Cool": "4876",
    "Good": "739",
    "Bad": "13",
    "Miss": "48",
    "MaxCombo": "1215",
    "Acc": "89.16%",
    "Progress": "B Rank",
    "Clear": "Cleared",
    "PlayTime": "2022-10-11 21:43:21"
  },
  {
    "UserID": "5408",
    "Nickname": "로스트쿨",
    "Cool": "4968",
    "Good": "638",
    "Bad": "9",
    "Miss": "61",
    "MaxCombo": "916",
    "Acc": "87.89%",
    "Progress": "B Rank",
    "Clear": "Cleared",
    "PlayTime": "2022-10-02 17:44:23"
  },
  {
    "UserID": "1166",
    "Nickname": "Delly.K",
    "Cool": "4839",
    "Good": "750",
    "Bad": "8",
    "Miss": "79",
    "MaxCombo": "1223",
    "Acc": "85.02%",
    "Progress": "C Rank",
    "Clear": "Cleared",
    "PlayTime": "2022-07-26 04:47:31"
  },
  {
    "UserID": "136",
    "Nickname": "시각",
    "Cool": "5054",
    "Good": "530",
    "Bad": "25",
    "Miss": "67",
    "MaxCombo": "1433",
    "Acc": "84.57%",
    "Progress": "C Rank",
    "Clear": "Cleared",
    "PlayTime": "2022-06-17 16:41:19"
  },
  {
    "UserID": "1169",
    "Nickname": "Nori",
    "Cool": "4632",
    "Good": "955",
    "Bad": "9",
    "Miss": "80",
    "MaxCombo": "1193",
    "Acc": "84.37%",
    "Progress": "C Rank",
    "Clear": "Cleared",
    "PlayTime": "2021-12-20 17:36:46"
  },
  {
    "UserID": "148",
    "Nickname": "뽕",
    "Cool": "4447",
    "Good": "1138",
    "Bad": "4",
    "Miss": "87",
    "MaxCombo": "862",
    "Acc": "83.77%",
    "Progress": "C Rank",
    "Clear": "Cleared",
    "PlayTime": "2022-05-28 23:13:17"
  },
  {
    "UserID": "2260",
    "Nickname": "짜이우",
    "Cool": "4157",
    "Good": "1421",
    "Bad": "13",
    "Miss": "85",
    "MaxCombo": "817",
    "Acc": "82.21%",
    "Progress": "C Rank",
    "Clear": "Cleared",
    "PlayTime": "2021-12-25 21:21:22"
  },
  {
    "UserID": "72",
    "Nickname": "햇살",
    "Cool": "4561",
    "Good": "997",
    "Bad": "34",
    "Miss": "84",
    "MaxCombo": "635",
    "Acc": "79.71%",
    "Progress": "C Rank",
    "Clear": "Cleared",
    "PlayTime": "2022-05-09 19:00:49"
  },
  {
    "UserID": "139",
    "Nickname": "아크네스",
    "Cool": "4891",
    "Good": "654",
    "Bad": "15",
    "Miss": "116",
    "MaxCombo": "640",
    "Acc": "78.19%",
    "Progress": "C Rank",
    "Clear": "Cleared",
    "PlayTime": "2021-12-19 18:45:12"
  },
  {
    "UserID": "4",
    "Nickname": "DP_",
    "Cool": "4689",
    "Good": "849",
    "Bad": "40",
    "Miss": "98",
    "MaxCombo": "760",
    "Acc": "76.77%",
    "Progress": "D Rank",
    "Clear": "Cleared",
    "PlayTime": "2022-08-08 00:20:41"
  },
  {
    "UserID": "1195",
    "Nickname": "Destiny19",
    "Cool": "4735",
    "Good": "799",
    "Bad": "29",
    "Miss": "113",
    "MaxCombo": "726",
    "Acc": "76.22%",
    "Progress": "D Rank",
    "Clear": "Cleared",
    "PlayTime": "2022-06-17 16:41:19"
  },
  {
    "UserID": "1223",
    "Nickname": "Sanni",
    "Cool": "4360",
    "Good": "1176",
    "Bad": "26",
    "Miss": "114",
    "MaxCombo": "566",
    "Acc": "75.94%",
    "Progress": "D Rank",
    "Clear": "Cleared",
    "PlayTime": "2022-07-22 23:50:58"
  },
  {
    "UserID": "1200",
    "Nickname": "무",
    "Cool": "4282",
    "Good": "1226",
    "Bad": "42",
    "Miss": "126",
    "MaxCombo": "409",
    "Acc": "71.42%",
    "Progress": "D Rank",
    "Clear": "Cleared",
    "PlayTime": "2022-06-04 21:52:20"
  },
  {
    "UserID": "85",
    "Nickname": "Royal777",
    "Cool": "4257",
    "Good": "1152",
    "Bad": "39",
    "Miss": "154",
    "MaxCombo": "737",
    "Acc": "44.67%",
    "Progress": "F Rank",
    "Clear": "Failed",
    "PlayTime": "2022-11-19 18:03:17"
  },
  {
    "UserID": "5561",
    "Nickname": "베리",
    "Cool": "4328",
    "Good": "1018",
    "Bad": "54",
    "Miss": "120",
    "MaxCombo": "561",
    "Acc": "36.85%",
    "Progress": "F Rank",
    "Clear": "Failed",
    "PlayTime": "2022-10-15 22:49:21"
  },
  {
    "UserID": "75",
    "Nickname": "dew",
    "Cool": "3915",
    "Good": "1404",
    "Bad": "42",
    "Miss": "116",
    "MaxCombo": "727",
    "Acc": "32.93%",
    "Progress": "F Rank",
    "Clear": "Failed",
    "PlayTime": "2022-10-16 22:36:01"
  },
  {
    "UserID": "5605",
    "Nickname": "제노",
    "Cool": "4016",
    "Good": "1218",
    "Bad": "44",
    "Miss": "150",
    "MaxCombo": "620",
    "Acc": "22.39%",
    "Progress": "F Rank",
    "Clear": "Failed",
    "PlayTime": "2022-10-28 16:33:30"
  },
  {
    "UserID": "5585",
    "Nickname": "ShinSa",
    "Cool": "3945",
    "Good": "878",
    "Bad": "32",
    "Miss": "125",
    "MaxCombo": "440",
    "Acc": "7.54%",
    "Progress": "F Rank",
    "Clear": "Failed",
    "PlayTime": "2022-11-05 03:54:14"
  },
  {
    "UserID": "5390",
    "Nickname": "Myzki",
    "Cool": "3550",
    "Good": "702",
    "Bad": "32",
    "Miss": "110",
    "MaxCombo": "734",
    "Acc": "6.65%",
    "Progress": "F Rank",
    "Clear": "Failed",
    "PlayTime": "2022-06-14 18:54:52"
  },
  {
    "UserID": "1202",
    "Nickname": "뜌",
    "Cool": "2889",
    "Good": "970",
    "Bad": "26",
    "Miss": "106",
    "MaxCombo": "526",
    "Acc": "6.03%",
    "Progress": "F Rank",
    "Clear": "Failed",
    "PlayTime": "2021-12-29 15:41:14"
  },
  {
    "UserID": "2317",
    "Nickname": "Up",
    "Cool": "2345",
    "Good": "888",
    "Bad": "61",
    "Miss": "93",
    "MaxCombo": "435",
    "Acc": "5.05%",
    "Progress": "F Rank",
    "Clear": "Failed",
    "PlayTime": "2022-05-11 04:32:56"
  },
  {
    "UserID": "5626",
    "Nickname": "anti",
    "Cool": "2418",
    "Good": "760",
    "Bad": "43",
    "Miss": "64",
    "MaxCombo": "608",
    "Acc": "4.96%",
    "Progress": "F Rank",
    "Clear": "Failed",
    "PlayTime": "2022-07-01 18:30:35"
  },
  {
    "UserID": "6017",
    "Nickname": "SanniFanGirl",
    "Cool": "2414",
    "Good": "710",
    "Bad": "53",
    "Miss": "77",
    "MaxCombo": "228",
    "Acc": "4.88%",
    "Progress": "F Rank",
    "Clear": "Failed",
    "PlayTime": "2022-09-29 00:09:00"
  },
  {
    "UserID": "5510",
    "Nickname": "숮",
    "Cool": "2353",
    "Good": "757",
    "Bad": "41",
    "Miss": "83",
    "MaxCombo": "573",
    "Acc": "4.86%",
    "Progress": "F Rank",
    "Clear": "Failed",
    "PlayTime": "2022-09-19 15:24:12"
  },
  {
    "UserID": "1222",
    "Nickname": "자라나라머리",
    "Cool": "2567",
    "Good": "529",
    "Bad": "38",
    "Miss": "101",
    "MaxCombo": "704",
    "Acc": "4.84%",
    "Progress": "F Rank",
    "Clear": "Failed",
    "PlayTime": "2022-09-10 04:42:19"
  },
  {
    "UserID": "6114",
    "Nickname": "레이븐",
    "Cool": "2262",
    "Good": "815",
    "Bad": "28",
    "Miss": "92",
    "MaxCombo": "484",
    "Acc": "4.81%",
    "Progress": "F Rank",
    "Clear": "Failed",
    "PlayTime": "2022-10-21 17:29:59"
  },
  {
    "UserID": "1173",
    "Nickname": "SuperPlay",
    "Cool": "1964",
    "Good": "1101",
    "Bad": "77",
    "Miss": "69",
    "MaxCombo": "351",
    "Acc": "4.78%",
    "Progress": "F Rank",
    "Clear": "Failed",
    "PlayTime": "2022-01-25 04:50:41"
  },
  {
    "UserID": "2313",
    "Nickname": "KenZ",
    "Cool": "2529",
    "Good": "503",
    "Bad": "25",
    "Miss": "86",
    "MaxCombo": "412",
    "Acc": "4.74%",
    "Progress": "F Rank",
    "Clear": "Failed",
    "PlayTime": "2022-12-04 13:09:05"
  },
  {
    "UserID": "6065",
    "Nickname": "LASvegas",
    "Cool": "2131",
    "Good": "893",
    "Bad": "59",
    "Miss": "78",
    "MaxCombo": "402",
    "Acc": "4.72%",
    "Progress": "F Rank",
    "Clear": "Failed",
    "PlayTime": "2022-06-07 23:55:26"
  },
  {
    "UserID": "6424",
    "Nickname": "Dipif",
    "Cool": "2266",
    "Good": "644",
    "Bad": "49",
    "Miss": "85",
    "MaxCombo": "365",
    "Acc": "4.55%",
    "Progress": "F Rank",
    "Clear": "Failed",
    "PlayTime": "2022-06-13 21:34:02"
  },
  {
    "UserID": "6022",
    "Nickname": "retyxrk",
    "Cool": "2546",
    "Good": "361",
    "Bad": "36",
    "Miss": "61",
    "MaxCombo": "664",
    "Acc": "4.55%",
    "Progress": "F Rank",
    "Clear": "Failed",
    "PlayTime": "2022-03-05 17:14:22"
  },
  {
    "UserID": "5359",
    "Nickname": "WaKa",
    "Cool": "2022",
    "Good": "875",
    "Bad": "39",
    "Miss": "83",
    "MaxCombo": "339",
    "Acc": "4.52%",
    "Progress": "F Rank",
    "Clear": "Failed",
    "PlayTime": "2021-12-19 16:35:00"
  },
  {
    "UserID": "2293",
    "Nickname": "ideu",
    "Cool": "2241",
    "Good": "625",
    "Bad": "14",
    "Miss": "84",
    "MaxCombo": "352",
    "Acc": "4.48%",
    "Progress": "F Rank",
    "Clear": "Failed",
    "PlayTime": "2021-12-18 21:55:11"
  },
  {
    "UserID": "5463",
    "Nickname": "Nyooo",
    "Cool": "1836",
    "Good": "1032",
    "Bad": "73",
    "Miss": "65",
    "MaxCombo": "456",
    "Acc": "4.48%",
    "Progress": "F Rank",
    "Clear": "Failed",
    "PlayTime": "2022-05-01 21:59:18"
  },
  {
    "UserID": "5644",
    "Nickname": "hfff",
    "Cool": "2365",
    "Good": "486",
    "Bad": "56",
    "Miss": "83",
    "MaxCombo": "470",
    "Acc": "4.46%",
    "Progress": "F Rank",
    "Clear": "Failed",
    "PlayTime": "2022-10-06 21:33:03"
  },
  {
    "UserID": "1204",
    "Nickname": "거미",
    "Cool": "2241",
    "Good": "611",
    "Bad": "15",
    "Miss": "91",
    "MaxCombo": "343",
    "Acc": "4.46%",
    "Progress": "F Rank",
    "Clear": "Failed",
    "PlayTime": "2022-01-06 18:31:01"
  },
  {
    "UserID": "5449",
    "Nickname": "Akayro",
    "Cool": "2316",
    "Good": "518",
    "Bad": "21",
    "Miss": "90",
    "MaxCombo": "408",
    "Acc": "4.43%",
    "Progress": "F Rank",
    "Clear": "Failed",
    "PlayTime": "2021-12-29 03:28:29"
  },
  {
    "UserID": "5677",
    "Nickname": "kimth",
    "Cool": "2140",
    "Good": "631",
    "Bad": "45",
    "Miss": "91",
    "MaxCombo": "305",
    "Acc": "4.33%",
    "Progress": "F Rank",
    "Clear": "Failed",
    "PlayTime": "2022-09-02 00:37:38"
  },
  {
    "UserID": "2237",
    "Nickname": "모모로",
    "Cool": "1901",
    "Good": "871",
    "Bad": "55",
    "Miss": "76",
    "MaxCombo": "372",
    "Acc": "4.33%",
    "Progress": "F Rank",
    "Clear": "Failed",
    "PlayTime": "2022-01-13 02:35:10"
  },
  {
    "UserID": "5655",
    "Nickname": "Soomin",
    "Cool": "1878",
    "Good": "889",
    "Bad": "57",
    "Miss": "79",
    "MaxCombo": "302",
    "Acc": "4.32%",
    "Progress": "F Rank",
    "Clear": "Failed",
    "PlayTime": "2022-01-28 16:17:45"
  },
  {
    "UserID": "2271",
    "Nickname": "sorakara",
    "Cool": "2220",
    "Good": "529",
    "Bad": "37",
    "Miss": "72",
    "MaxCombo": "399",
    "Acc": "4.3%",
    "Progress": "F Rank",
    "Clear": "Failed",
    "PlayTime": "2022-02-15 20:52:27"
  },
  {
    "UserID": "1181",
    "Nickname": "못하는톰",
    "Cool": "2000",
    "Good": "726",
    "Bad": "27",
    "Miss": "78",
    "MaxCombo": "390",
    "Acc": "4.26%",
    "Progress": "F Rank",
    "Clear": "Failed",
    "PlayTime": "2021-12-22 17:23:55"
  },
  {
    "UserID": "5397",
    "Nickname": "nadekodayo",
    "Cool": "2009",
    "Good": "686",
    "Bad": "26",
    "Miss": "75",
    "MaxCombo": "498",
    "Acc": "4.21%",
    "Progress": "F Rank",
    "Clear": "Failed",
    "PlayTime": "2022-03-06 20:16:54"
  },
  {
    "UserID": "16",
    "Nickname": "지존기병장장",
    "Cool": "1824",
    "Good": "722",
    "Bad": "7",
    "Miss": "75",
    "MaxCombo": "667",
    "Acc": "3.98%",
    "Progress": "F Rank",
    "Clear": "Failed",
    "PlayTime": "2022-10-22 18:48:39"
  },
  {
    "UserID": "2279",
    "Nickname": "dadots123",
    "Cool": "1911",
    "Good": "542",
    "Bad": "33",
    "Miss": "84",
    "MaxCombo": "350",
    "Acc": "3.83%",
    "Progress": "F Rank",
    "Clear": "Failed",
    "PlayTime": "2022-11-08 22:03:55"
  },
  {
    "UserID": "5383",
    "Nickname": "NLwI",
    "Cool": "1880",
    "Good": "568",
    "Bad": "1",
    "Miss": "88",
    "MaxCombo": "210",
    "Acc": "3.82%",
    "Progress": "F Rank",
    "Clear": "Failed",
    "PlayTime": "2022-07-05 19:52:00"
  },
  {
    "UserID": "3327",
    "Nickname": "WNCC",
    "Cool": "1885",
    "Good": "357",
    "Bad": "14",
    "Miss": "89",
    "MaxCombo": "226",
    "Acc": "3.51%",
    "Progress": "F Rank",
    "Clear": "Failed",
    "PlayTime": "2022-04-26 19:35:16"
  },
  {
    "UserID": "6542",
    "Nickname": "해바라기",
    "Cool": "1786",
    "Good": "448",
    "Bad": "32",
    "Miss": "72",
    "MaxCombo": "404",
    "Acc": "3.49%",
    "Progress": "F Rank",
    "Clear": "Failed",
    "PlayTime": "2022-10-29 18:23:37"
  },
  {
    "UserID": "1229",
    "Nickname": "LCH",
    "Cool": "1808",
    "Good": "384",
    "Bad": "4",
    "Miss": "74",
    "MaxCombo": "664",
    "Acc": "3.43%",
    "Progress": "F Rank",
    "Clear": "Failed",
    "PlayTime": "2022-10-16 17:18:10"
  },
  {
    "UserID": "6470",
    "Nickname": "ene",
    "Cool": "1698",
    "Good": "485",
    "Bad": "8",
    "Miss": "76",
    "MaxCombo": "186",
    "Acc": "3.41%",
    "Progress": "F Rank",
    "Clear": "Failed",
    "PlayTime": "2022-06-29 00:33:49"
  },
  {
    "UserID": "97",
    "Nickname": "Nazo",
    "Cool": "1763",
    "Good": "396",
    "Bad": "0",
    "Miss": "82",
    "MaxCombo": "340",
    "Acc": "3.37%",
    "Progress": "F Rank",
    "Clear": "Failed",
    "PlayTime": "2022-06-07 23:42:34"
  },
  {
    "UserID": "5813",
    "Nickname": "스알",
    "Cool": "1622",
    "Good": "455",
    "Bad": "50",
    "Miss": "75",
    "MaxCombo": "173",
    "Acc": "3.25%",
    "Progress": "F Rank",
    "Clear": "Failed",
    "PlayTime": "2021-12-19 01:26:35"
  },
  {
    "UserID": "6419",
    "Nickname": "엔트리아",
    "Cool": "1361",
    "Good": "681",
    "Bad": "40",
    "Miss": "69",
    "MaxCombo": "176",
    "Acc": "3.19%",
    "Progress": "F Rank",
    "Clear": "Failed",
    "PlayTime": "2022-04-04 11:54:27"
  },
  {
    "UserID": "5822",
    "Nickname": "실존하는허수",
    "Cool": "1544",
    "Good": "472",
    "Bad": "19",
    "Miss": "72",
    "MaxCombo": "290",
    "Acc": "3.15%",
    "Progress": "F Rank",
    "Clear": "Failed",
    "PlayTime": "2021-12-19 01:26:35"
  },
  {
    "UserID": "2233",
    "Nickname": "Bero",
    "Cool": "1523",
    "Good": "462",
    "Bad": "12",
    "Miss": "70",
    "MaxCombo": "387",
    "Acc": "3.1%",
    "Progress": "F Rank",
    "Clear": "Failed",
    "PlayTime": "2022-02-20 01:22:36"
  },
  {
    "UserID": "1179",
    "Nickname": "성공임",
    "Cool": "1527",
    "Good": "378",
    "Bad": "19",
    "Miss": "72",
    "MaxCombo": "229",
    "Acc": "2.98%",
    "Progress": "F Rank",
    "Clear": "Failed",
    "PlayTime": "2022-05-02 16:42:53"
  },
  {
    "UserID": "2265",
    "Nickname": "제아롯드",
    "Cool": "1169",
    "Good": "347",
    "Bad": "18",
    "Miss": "63",
    "MaxCombo": "239",
    "Acc": "2.37%",
    "Progress": "F Rank",
    "Clear": "Failed",
    "PlayTime": "2021-12-28 23:00:28"
  },
  {
    "UserID": "165",
    "Nickname": "Chess",
    "Cool": "1195",
    "Good": "305",
    "Bad": "29",
    "Miss": "63",
    "MaxCombo": "153",
    "Acc": "2.34%",
    "Progress": "F Rank",
    "Clear": "Failed",
    "PlayTime": "2022-03-19 19:09:05"
  },
  {
    "UserID": "5428",
    "Nickname": "푸푸민우",
    "Cool": "1088",
    "Good": "409",
    "Bad": "36",
    "Miss": "57",
    "MaxCombo": "203",
    "Acc": "2.34%",
    "Progress": "F Rank",
    "Clear": "Failed",
    "PlayTime": "2021-12-19 01:26:35"
  },
  {
    "UserID": "5364",
    "Nickname": "페카",
    "Cool": "1097",
    "Good": "357",
    "Bad": "30",
    "Miss": "57",
    "MaxCombo": "167",
    "Acc": "2.27%",
    "Progress": "F Rank",
    "Clear": "Failed",
    "PlayTime": "2021-12-28 23:00:28"
  },
  {
    "UserID": "6050",
    "Nickname": "짬키",
    "Cool": "951",
    "Good": "318",
    "Bad": "30",
    "Miss": "58",
    "MaxCombo": "148",
    "Acc": "1.98%",
    "Progress": "F Rank",
    "Clear": "Failed",
    "PlayTime": "2022-08-31 18:52:06"
  },
  {
    "UserID": "5766",
    "Nickname": "Irish",
    "Cool": "409",
    "Good": "206",
    "Bad": "36",
    "Miss": "40",
    "MaxCombo": "65",
    "Acc": "0.96%",
    "Progress": "F Rank",
    "Clear": "Failed",
    "PlayTime": "2022-05-17 02:12:26"
  },
  {
    "UserID": "2324",
    "Nickname": "FullOptions",
    "Cool": "247",
    "Good": "234",
    "Bad": "18",
    "Miss": "37",
    "MaxCombo": "75",
    "Acc": "0.75%",
    "Progress": "F Rank",
    "Clear": "Failed",
    "PlayTime": "2021-12-21 21:24:44"
  },
  {
    "UserID": "6535",
    "Nickname": "꾸꾸",
    "Cool": "205",
    "Good": "126",
    "Bad": "26",
    "Miss": "35",
    "MaxCombo": "46",
    "Acc": "0.52%",
    "Progress": "F Rank",
    "Clear": "Failed",
    "PlayTime": "2022-11-06 23:17:43"
  },
  {
    "UserID": "1183",
    "Nickname": "SacredReisen",
    "Cool": "171",
    "Good": "61",
    "Bad": "0",
    "Miss": "38",
    "MaxCombo": "70",
    "Acc": "0.36%",
    "Progress": "F Rank",
    "Clear": "Failed",
    "PlayTime": "2022-05-19 22:42:25"
  }
]