[
  {
    "UserID": "5561",
    "Nickname": "베리",
    "Cool": "4462",
    "Good": "92",
    "Bad": "0",
    "Miss": "9",
    "MaxCombo": "1806",
    "Acc": "98.04%",
    "Progress": "S Rank",
    "Clear": "Cleared",
    "PlayTime": "2022-09-19 23:48:25"
  },
  {
    "UserID": "5408",
    "Nickname": "로스트쿨",
    "Cool": "4412",
    "Good": "137",
    "Bad": "0",
    "Miss": "14",
    "MaxCombo": "1600",
    "Acc": "96.97%",
    "Progress": "S Rank",
    "Clear": "Cleared",
    "PlayTime": "2022-09-11 17:34:12"
  },
  {
    "UserID": "1166",
    "Nickname": "Delly.K",
    "Cool": "4332",
    "Good": "215",
    "Bad": "0",
    "Miss": "16",
    "MaxCombo": "1817",
    "Acc": "96.42%",
    "Progress": "S Rank",
    "Clear": "Cleared",
    "PlayTime": "2022-09-16 22:05:03"
  },
  {
    "UserID": "85",
    "Nickname": "Royal777",
    "Cool": "4210",
    "Good": "320",
    "Bad": "1",
    "Miss": "32",
    "MaxCombo": "863",
    "Acc": "92.86%",
    "Progress": "A Rank",
    "Clear": "Cleared",
    "PlayTime": "2022-11-26 16:45:22"
  },
  {
    "UserID": "4",
    "Nickname": "DP_",
    "Cool": "3508",
    "Good": "1026",
    "Bad": "2",
    "Miss": "27",
    "MaxCombo": "1068",
    "Acc": "92.26%",
    "Progress": "A Rank",
    "Clear": "Cleared",
    "PlayTime": "2022-09-10 17:29:29"
  },
  {
    "UserID": "6470",
    "Nickname": "ene",
    "Cool": "3960",
    "Good": "552",
    "Bad": "0",
    "Miss": "51",
    "MaxCombo": "549",
    "Acc": "88.85%",
    "Progress": "B Rank",
    "Clear": "Cleared",
    "PlayTime": "2022-11-14 06:20:01"
  },
  {
    "UserID": "1183",
    "Nickname": "SacredReisen",
    "Cool": "4064",
    "Good": "441",
    "Bad": "0",
    "Miss": "58",
    "MaxCombo": "809",
    "Acc": "87.69%",
    "Progress": "B Rank",
    "Clear": "Cleared",
    "PlayTime": "2022-09-25 22:23:50"
  },
  {
    "UserID": "167",
    "Nickname": "rights",
    "Cool": "3882",
    "Good": "605",
    "Bad": "10",
    "Miss": "66",
    "MaxCombo": "925",
    "Acc": "83.82%",
    "Progress": "C Rank",
    "Clear": "Cleared",
    "PlayTime": "2022-12-04 22:54:29"
  },
  {
    "UserID": "1202",
    "Nickname": "뜌",
    "Cool": "4095",
    "Good": "386",
    "Bad": "21",
    "Miss": "61",
    "MaxCombo": "772",
    "Acc": "83.06%",
    "Progress": "C Rank",
    "Clear": "Cleared",
    "PlayTime": "2022-09-10 23:34:38"
  },
  {
    "UserID": "1222",
    "Nickname": "자라나라머리",
    "Cool": "3451",
    "Good": "1031",
    "Bad": "13",
    "Miss": "68",
    "MaxCombo": "889",
    "Acc": "81.99%",
    "Progress": "C Rank",
    "Clear": "Cleared",
    "PlayTime": "2022-09-21 07:01:53"
  },
  {
    "UserID": "6065",
    "Nickname": "LASvegas",
    "Cool": "3977",
    "Good": "494",
    "Bad": "17",
    "Miss": "75",
    "MaxCombo": "410",
    "Acc": "80.88%",
    "Progress": "C Rank",
    "Clear": "Cleared",
    "PlayTime": "2022-09-11 23:58:18"
  },
  {
    "UserID": "5501",
    "Nickname": "Angelina",
    "Cool": "3953",
    "Good": "514",
    "Bad": "3",
    "Miss": "93",
    "MaxCombo": "684",
    "Acc": "80.05%",
    "Progress": "C Rank",
    "Clear": "Cleared",
    "PlayTime": "2022-10-31 21:10:41"
  },
  {
    "UserID": "1181",
    "Nickname": "못하는톰",
    "Cool": "3540",
    "Good": "927",
    "Bad": "2",
    "Miss": "94",
    "MaxCombo": "537",
    "Acc": "79.24%",
    "Progress": "C Rank",
    "Clear": "Cleared",
    "PlayTime": "2022-11-26 21:12:13"
  },
  {
    "UserID": "5449",
    "Nickname": "Akayro",
    "Cool": "4143",
    "Good": "316",
    "Bad": "5",
    "Miss": "99",
    "MaxCombo": "530",
    "Acc": "78.86%",
    "Progress": "C Rank",
    "Clear": "Cleared",
    "PlayTime": "2022-11-16 04:41:42"
  },
  {
    "UserID": "2313",
    "Nickname": "KenZ",
    "Cool": "3722",
    "Good": "739",
    "Bad": "26",
    "Miss": "76",
    "MaxCombo": "466",
    "Acc": "78.42%",
    "Progress": "C Rank",
    "Clear": "Cleared",
    "PlayTime": "2022-12-09 15:35:47"
  },
  {
    "UserID": "2284",
    "Nickname": "Jance",
    "Cool": "3913",
    "Good": "545",
    "Bad": "21",
    "Miss": "84",
    "MaxCombo": "585",
    "Acc": "78.21%",
    "Progress": "C Rank",
    "Clear": "Cleared",
    "PlayTime": "2022-11-29 12:42:44"
  },
  {
    "UserID": "5351",
    "Nickname": "Neokje",
    "Cool": "3921",
    "Good": "536",
    "Bad": "15",
    "Miss": "91",
    "MaxCombo": "833",
    "Acc": "78.04%",
    "Progress": "C Rank",
    "Clear": "Cleared",
    "PlayTime": "2022-09-14 23:30:11"
  },
  {
    "UserID": "5605",
    "Nickname": "제노",
    "Cool": "3854",
    "Good": "595",
    "Bad": "24",
    "Miss": "90",
    "MaxCombo": "349",
    "Acc": "76.34%",
    "Progress": "D Rank",
    "Clear": "Cleared",
    "PlayTime": "2022-09-13 16:24:30"
  },
  {
    "UserID": "4348",
    "Nickname": "nadavv",
    "Cool": "3930",
    "Good": "493",
    "Bad": "18",
    "Miss": "122",
    "MaxCombo": "315",
    "Acc": "71.41%",
    "Progress": "D Rank",
    "Clear": "Cleared",
    "PlayTime": "2022-11-18 00:21:22"
  },
  {
    "UserID": "166",
    "Nickname": "DeepBlueSky",
    "Cool": "3436",
    "Good": "980",
    "Bad": "33",
    "Miss": "114",
    "MaxCombo": "463",
    "Acc": "69.07%",
    "Progress": "D Rank",
    "Clear": "Cleared",
    "PlayTime": "2022-10-30 02:49:03"
  },
  {
    "UserID": "5813",
    "Nickname": "스알",
    "Cool": "3553",
    "Good": "853",
    "Bad": "29",
    "Miss": "128",
    "MaxCombo": "484",
    "Acc": "67.35%",
    "Progress": "D Rank",
    "Clear": "Cleared",
    "PlayTime": "2022-09-10 23:26:28"
  },
  {
    "UserID": "5384",
    "Nickname": "돈까스트라이크",
    "Cool": "3817",
    "Good": "586",
    "Bad": "20",
    "Miss": "140",
    "MaxCombo": "336",
    "Acc": "67.29%",
    "Progress": "D Rank",
    "Clear": "Cleared",
    "PlayTime": "2022-10-02 13:39:22"
  },
  {
    "UserID": "5397",
    "Nickname": "nadekodayo",
    "Cool": "3077",
    "Good": "1012",
    "Bad": "11",
    "Miss": "119",
    "MaxCombo": "318",
    "Acc": "7.95%",
    "Progress": "F Rank",
    "Clear": "Failed",
    "PlayTime": "2022-11-26 21:12:13"
  },
  {
    "UserID": "1200",
    "Nickname": "무",
    "Cool": "3370",
    "Good": "469",
    "Bad": "9",
    "Miss": "116",
    "MaxCombo": "318",
    "Acc": "7.47%",
    "Progress": "F Rank",
    "Clear": "Failed",
    "PlayTime": "2022-09-30 20:01:46"
  },
  {
    "UserID": "5428",
    "Nickname": "푸푸민우",
    "Cool": "3106",
    "Good": "677",
    "Bad": "15",
    "Miss": "103",
    "MaxCombo": "523",
    "Acc": "7.36%",
    "Progress": "F Rank",
    "Clear": "Failed",
    "PlayTime": "2022-10-29 00:24:39"
  },
  {
    "UserID": "5673",
    "Nickname": "allen poknat",
    "Cool": "2856",
    "Good": "752",
    "Bad": "6",
    "Miss": "111",
    "MaxCombo": "289",
    "Acc": "7.01%",
    "Progress": "F Rank",
    "Clear": "Failed",
    "PlayTime": "2022-09-28 08:23:57"
  },
  {
    "UserID": "5892",
    "Nickname": "TakJunu",
    "Cool": "2928",
    "Good": "604",
    "Bad": "18",
    "Miss": "117",
    "MaxCombo": "223",
    "Acc": "6.87%",
    "Progress": "F Rank",
    "Clear": "Failed",
    "PlayTime": "2022-10-30 20:47:45"
  },
  {
    "UserID": "5620",
    "Nickname": "Niggy",
    "Cool": "2980",
    "Good": "512",
    "Bad": "41",
    "Miss": "120",
    "MaxCombo": "326",
    "Acc": "6.79%",
    "Progress": "F Rank",
    "Clear": "Failed",
    "PlayTime": "2022-10-21 23:41:14"
  },
  {
    "UserID": "3335",
    "Nickname": "gero",
    "Cool": "3072",
    "Good": "343",
    "Bad": "27",
    "Miss": "119",
    "MaxCombo": "336",
    "Acc": "6.65%",
    "Progress": "F Rank",
    "Clear": "Failed",
    "PlayTime": "2022-10-27 21:33:12"
  },
  {
    "UserID": "1221",
    "Nickname": "Wewoj",
    "Cool": "2799",
    "Good": "529",
    "Bad": "24",
    "Miss": "108",
    "MaxCombo": "421",
    "Acc": "6.47%",
    "Progress": "F Rank",
    "Clear": "Failed",
    "PlayTime": "2022-10-21 23:41:14"
  },
  {
    "UserID": "5477",
    "Nickname": "Zycrxd",
    "Cool": "2857",
    "Good": "463",
    "Bad": "8",
    "Miss": "107",
    "MaxCombo": "219",
    "Acc": "6.46%",
    "Progress": "F Rank",
    "Clear": "Failed",
    "PlayTime": "2022-09-30 07:20:15"
  },
  {
    "UserID": "6229",
    "Nickname": "FenIndraWijaya",
    "Cool": "2250",
    "Good": "863",
    "Bad": "30",
    "Miss": "98",
    "MaxCombo": "341",
    "Acc": "6.05%",
    "Progress": "F Rank",
    "Clear": "Failed",
    "PlayTime": "2022-09-23 10:35:59"
  },
  {
    "UserID": "165",
    "Nickname": "Chess",
    "Cool": "2466",
    "Good": "598",
    "Bad": "41",
    "Miss": "82",
    "MaxCombo": "645",
    "Acc": "5.96%",
    "Progress": "F Rank",
    "Clear": "Failed",
    "PlayTime": "2022-12-03 22:50:40"
  },
  {
    "UserID": "5600",
    "Nickname": "코스모스",
    "Cool": "2427",
    "Good": "534",
    "Bad": "4",
    "Miss": "95",
    "MaxCombo": "391",
    "Acc": "5.76%",
    "Progress": "F Rank",
    "Clear": "Failed",
    "PlayTime": "2022-09-23 01:46:38"
  },
  {
    "UserID": "2300",
    "Nickname": "그림자",
    "Cool": "2470",
    "Good": "404",
    "Bad": "18",
    "Miss": "98",
    "MaxCombo": "257",
    "Acc": "5.59%",
    "Progress": "F Rank",
    "Clear": "Failed",
    "PlayTime": "2022-10-21 14:52:38"
  },
  {
    "UserID": "5842",
    "Nickname": "Severity",
    "Cool": "2298",
    "Good": "444",
    "Bad": "31",
    "Miss": "74",
    "MaxCombo": "491",
    "Acc": "5.33%",
    "Progress": "F Rank",
    "Clear": "Failed",
    "PlayTime": "2022-10-11 03:50:05"
  },
  {
    "UserID": "6452",
    "Nickname": "Ayam88",
    "Cool": "2297",
    "Good": "384",
    "Bad": "15",
    "Miss": "81",
    "MaxCombo": "445",
    "Acc": "5.22%",
    "Progress": "F Rank",
    "Clear": "Failed",
    "PlayTime": "2022-12-04 22:44:35"
  },
  {
    "UserID": "5364",
    "Nickname": "페카",
    "Cool": "2273",
    "Good": "406",
    "Bad": "7",
    "Miss": "99",
    "MaxCombo": "297",
    "Acc": "5.21%",
    "Progress": "F Rank",
    "Clear": "Failed",
    "PlayTime": "2022-10-29 00:24:39"
  },
  {
    "UserID": "1225",
    "Nickname": "Bazzi",
    "Cool": "2272",
    "Good": "390",
    "Bad": "15",
    "Miss": "99",
    "MaxCombo": "279",
    "Acc": "5.18%",
    "Progress": "F Rank",
    "Clear": "Failed",
    "PlayTime": "2022-09-11 08:48:09"
  },
  {
    "UserID": "5609",
    "Nickname": "misuzu",
    "Cool": "1861",
    "Good": "763",
    "Bad": "10",
    "Miss": "69",
    "MaxCombo": "491",
    "Acc": "5.1%",
    "Progress": "F Rank",
    "Clear": "Failed",
    "PlayTime": "2022-10-13 21:56:17"
  },
  {
    "UserID": "2280",
    "Nickname": "MasterHell54",
    "Cool": "1837",
    "Good": "662",
    "Bad": "16",
    "Miss": "88",
    "MaxCombo": "268",
    "Acc": "4.86%",
    "Progress": "F Rank",
    "Clear": "Failed",
    "PlayTime": "2022-10-16 17:59:17"
  },
  {
    "UserID": "4345",
    "Nickname": "timebuka",
    "Cool": "2152",
    "Good": "331",
    "Bad": "13",
    "Miss": "87",
    "MaxCombo": "648",
    "Acc": "4.83%",
    "Progress": "F Rank",
    "Clear": "Failed",
    "PlayTime": "2022-11-23 05:32:22"
  },
  {
    "UserID": "5827",
    "Nickname": "워너비",
    "Cool": "2018",
    "Good": "450",
    "Bad": "29",
    "Miss": "91",
    "MaxCombo": "253",
    "Acc": "4.8%",
    "Progress": "F Rank",
    "Clear": "Failed",
    "PlayTime": "2022-09-17 16:09:48"
  },
  {
    "UserID": "2256",
    "Nickname": "SeoDae",
    "Cool": "2052",
    "Good": "396",
    "Bad": "34",
    "Miss": "92",
    "MaxCombo": "269",
    "Acc": "4.76%",
    "Progress": "F Rank",
    "Clear": "Failed",
    "PlayTime": "2022-10-30 04:18:21"
  },
  {
    "UserID": "5529",
    "Nickname": "ZYuan",
    "Cool": "2042",
    "Good": "329",
    "Bad": "53",
    "Miss": "87",
    "MaxCombo": "217",
    "Acc": "4.61%",
    "Progress": "F Rank",
    "Clear": "Failed",
    "PlayTime": "2022-09-14 23:30:11"
  },
  {
    "UserID": "75",
    "Nickname": "dew",
    "Cool": "1982",
    "Good": "313",
    "Bad": "6",
    "Miss": "71",
    "MaxCombo": "564",
    "Acc": "4.46%",
    "Progress": "F Rank",
    "Clear": "Failed",
    "PlayTime": "2022-10-03 21:15:33"
  },
  {
    "UserID": "1195",
    "Nickname": "Destiny19",
    "Cool": "1715",
    "Good": "570",
    "Bad": "19",
    "Miss": "69",
    "MaxCombo": "448",
    "Acc": "4.44%",
    "Progress": "F Rank",
    "Clear": "Failed",
    "PlayTime": "2022-11-21 22:07:47"
  },
  {
    "UserID": "2296",
    "Nickname": "Soul",
    "Cool": "1911",
    "Good": "371",
    "Bad": "43",
    "Miss": "86",
    "MaxCombo": "257",
    "Acc": "4.44%",
    "Progress": "F Rank",
    "Clear": "Failed",
    "PlayTime": "2022-12-07 14:06:23"
  },
  {
    "UserID": "6021",
    "Nickname": "phk329",
    "Cool": "1961",
    "Good": "256",
    "Bad": "25",
    "Miss": "83",
    "MaxCombo": "275",
    "Acc": "4.31%",
    "Progress": "F Rank",
    "Clear": "Failed",
    "PlayTime": "2022-10-28 02:22:21"
  },
  {
    "UserID": "6025",
    "Nickname": "넨시",
    "Cool": "1650",
    "Good": "544",
    "Bad": "34",
    "Miss": "75",
    "MaxCombo": "261",
    "Acc": "4.26%",
    "Progress": "F Rank",
    "Clear": "Failed",
    "PlayTime": "2022-12-03 22:50:40"
  },
  {
    "UserID": "2283",
    "Nickname": "Aili",
    "Cool": "1794",
    "Good": "378",
    "Bad": "14",
    "Miss": "85",
    "MaxCombo": "221",
    "Acc": "4.22%",
    "Progress": "F Rank",
    "Clear": "Failed",
    "PlayTime": "2022-12-11 12:31:16"
  },
  {
    "UserID": "2279",
    "Nickname": "dadots123",
    "Cool": "1850",
    "Good": "283",
    "Bad": "14",
    "Miss": "84",
    "MaxCombo": "230",
    "Acc": "4.15%",
    "Progress": "F Rank",
    "Clear": "Failed",
    "PlayTime": "2022-10-06 11:47:44"
  },
  {
    "UserID": "2312",
    "Nickname": "VFB",
    "Cool": "1912",
    "Good": "207",
    "Bad": "5",
    "Miss": "94",
    "MaxCombo": "251",
    "Acc": "4.12%",
    "Progress": "F Rank",
    "Clear": "Failed",
    "PlayTime": "2022-10-07 19:43:40"
  },
  {
    "UserID": "5996",
    "Nickname": "Tweyensorn",
    "Cool": "1605",
    "Good": "455",
    "Bad": "39",
    "Miss": "68",
    "MaxCombo": "374",
    "Acc": "4.0%",
    "Progress": "F Rank",
    "Clear": "Failed",
    "PlayTime": "2022-10-04 21:23:02"
  },
  {
    "UserID": "5510",
    "Nickname": "숮",
    "Cool": "1755",
    "Good": "142",
    "Bad": "6",
    "Miss": "41",
    "MaxCombo": "880",
    "Acc": "3.69%",
    "Progress": "F Rank",
    "Clear": "Failed",
    "PlayTime": "2022-11-04 12:57:11"
  },
  {
    "UserID": "5585",
    "Nickname": "ShinSa",
    "Cool": "1670",
    "Good": "193",
    "Bad": "9",
    "Miss": "65",
    "MaxCombo": "497",
    "Acc": "3.63%",
    "Progress": "F Rank",
    "Clear": "Failed",
    "PlayTime": "2022-10-30 04:18:21"
  },
  {
    "UserID": "2272",
    "Nickname": "skswkd",
    "Cool": "1533",
    "Good": "305",
    "Bad": "2",
    "Miss": "80",
    "MaxCombo": "198",
    "Acc": "3.57%",
    "Progress": "F Rank",
    "Clear": "Failed",
    "PlayTime": "2022-09-11 18:37:16"
  },
  {
    "UserID": "5803",
    "Nickname": "티아고",
    "Cool": "1478",
    "Good": "345",
    "Bad": "11",
    "Miss": "76",
    "MaxCombo": "228",
    "Acc": "3.54%",
    "Progress": "F Rank",
    "Clear": "Failed",
    "PlayTime": "2022-09-23 04:22:25"
  },
  {
    "UserID": "5383",
    "Nickname": "NLwI",
    "Cool": "1579",
    "Good": "229",
    "Bad": "26",
    "Miss": "78",
    "MaxCombo": "175",
    "Acc": "3.52%",
    "Progress": "F Rank",
    "Clear": "Failed",
    "PlayTime": "2022-10-20 19:09:59"
  },
  {
    "UserID": "5840",
    "Nickname": "Summit",
    "Cool": "1455",
    "Good": "352",
    "Bad": "16",
    "Miss": "77",
    "MaxCombo": "250",
    "Acc": "3.51%",
    "Progress": "F Rank",
    "Clear": "Failed",
    "PlayTime": "2022-09-27 03:30:53"
  },
  {
    "UserID": "6484",
    "Nickname": "RevVo",
    "Cool": "1494",
    "Good": "304",
    "Bad": "39",
    "Miss": "74",
    "MaxCombo": "124",
    "Acc": "3.5%",
    "Progress": "F Rank",
    "Clear": "Failed",
    "PlayTime": "2022-09-23 10:35:59"
  },
  {
    "UserID": "6303",
    "Nickname": "Tsukiya.Whiskers",
    "Cool": "1519",
    "Good": "276",
    "Bad": "40",
    "Miss": "73",
    "MaxCombo": "157",
    "Acc": "3.49%",
    "Progress": "F Rank",
    "Clear": "Failed",
    "PlayTime": "2022-10-18 02:44:37"
  },
  {
    "UserID": "1179",
    "Nickname": "성공임",
    "Cool": "1432",
    "Good": "354",
    "Bad": "10",
    "Miss": "75",
    "MaxCombo": "183",
    "Acc": "3.47%",
    "Progress": "F Rank",
    "Clear": "Failed",
    "PlayTime": "2022-11-10 15:21:44"
  },
  {
    "UserID": "4342",
    "Nickname": "HassanAli",
    "Cool": "1429",
    "Good": "350",
    "Bad": "26",
    "Miss": "73",
    "MaxCombo": "251",
    "Acc": "3.46%",
    "Progress": "F Rank",
    "Clear": "Failed",
    "PlayTime": "2022-12-07 20:08:44"
  },
  {
    "UserID": "4332",
    "Nickname": "mentor",
    "Cool": "1315",
    "Good": "462",
    "Bad": "13",
    "Miss": "70",
    "MaxCombo": "556",
    "Acc": "3.45%",
    "Progress": "F Rank",
    "Clear": "Failed",
    "PlayTime": "2022-09-11 15:05:36"
  },
  {
    "UserID": "5687",
    "Nickname": "CreamyKipay",
    "Cool": "1372",
    "Good": "393",
    "Bad": "7",
    "Miss": "75",
    "MaxCombo": "206",
    "Acc": "3.43%",
    "Progress": "F Rank",
    "Clear": "Failed",
    "PlayTime": "2022-09-25 20:37:47"
  },
  {
    "UserID": "6435",
    "Nickname": "bojjj",
    "Cool": "1297",
    "Good": "430",
    "Bad": "29",
    "Miss": "66",
    "MaxCombo": "176",
    "Acc": "3.36%",
    "Progress": "F Rank",
    "Clear": "Failed",
    "PlayTime": "2022-11-10 19:55:00"
  },
  {
    "UserID": "2237",
    "Nickname": "모모로",
    "Cool": "1310",
    "Good": "107",
    "Bad": "0",
    "Miss": "36",
    "MaxCombo": "852",
    "Acc": "2.76%",
    "Progress": "F Rank",
    "Clear": "Failed",
    "PlayTime": "2022-12-12 00:38:03"
  },
  {
    "UserID": "6606",
    "Nickname": "Leoca",
    "Cool": "1048",
    "Good": "321",
    "Bad": "1",
    "Miss": "61",
    "MaxCombo": "196",
    "Acc": "2.66%",
    "Progress": "F Rank",
    "Clear": "Failed",
    "PlayTime": "2022-11-07 10:14:10"
  },
  {
    "UserID": "5909",
    "Nickname": "Lachryma",
    "Cool": "1161",
    "Good": "88",
    "Bad": "9",
    "Miss": "66",
    "MaxCombo": "195",
    "Acc": "2.43%",
    "Progress": "F Rank",
    "Clear": "Failed",
    "PlayTime": "2022-10-22 18:36:13"
  },
  {
    "UserID": "2263",
    "Nickname": "Eve",
    "Cool": "948",
    "Good": "303",
    "Bad": "19",
    "Miss": "56",
    "MaxCombo": "226",
    "Acc": "2.43%",
    "Progress": "F Rank",
    "Clear": "Failed",
    "PlayTime": "2022-10-12 12:50:04"
  },
  {
    "UserID": "4326",
    "Nickname": "BananenTropfen",
    "Cool": "1010",
    "Good": "187",
    "Bad": "1",
    "Miss": "62",
    "MaxCombo": "180",
    "Acc": "2.33%",
    "Progress": "F Rank",
    "Clear": "Failed",
    "PlayTime": "2022-11-26 03:31:21"
  },
  {
    "UserID": "3327",
    "Nickname": "WNCC",
    "Cool": "931",
    "Good": "204",
    "Bad": "17",
    "Miss": "59",
    "MaxCombo": "160",
    "Acc": "2.21%",
    "Progress": "F Rank",
    "Clear": "Failed",
    "PlayTime": "2022-09-11 06:21:34"
  },
  {
    "UserID": "2324",
    "Nickname": "FullOptions",
    "Cool": "931",
    "Good": "164",
    "Bad": "19",
    "Miss": "59",
    "MaxCombo": "134",
    "Acc": "2.13%",
    "Progress": "F Rank",
    "Clear": "Failed",
    "PlayTime": "2022-10-11 03:46:04"
  },
  {
    "UserID": "6561",
    "Nickname": "Cyleigh",
    "Cool": "799",
    "Good": "288",
    "Bad": "0",
    "Miss": "56",
    "MaxCombo": "145",
    "Acc": "2.11%",
    "Progress": "F Rank",
    "Clear": "Failed",
    "PlayTime": "2022-12-07 20:08:44"
  },
  {
    "UserID": "6341",
    "Nickname": "Hyojin",
    "Cool": "893",
    "Good": "179",
    "Bad": "21",
    "Miss": "54",
    "MaxCombo": "194",
    "Acc": "2.08%",
    "Progress": "F Rank",
    "Clear": "Failed",
    "PlayTime": "2022-12-12 00:38:03"
  },
  {
    "UserID": "4338",
    "Nickname": "CratyII",
    "Cool": "773",
    "Good": "287",
    "Bad": "24",
    "Miss": "52",
    "MaxCombo": "170",
    "Acc": "2.06%",
    "Progress": "F Rank",
    "Clear": "Failed",
    "PlayTime": "2022-09-13 04:45:26"
  },
  {
    "UserID": "2328",
    "Nickname": "★Kakuri",
    "Cool": "738",
    "Good": "275",
    "Bad": "9",
    "Miss": "56",
    "MaxCombo": "154",
    "Acc": "1.97%",
    "Progress": "F Rank",
    "Clear": "Failed",
    "PlayTime": "2022-11-06 01:11:55"
  },
  {
    "UserID": "5799",
    "Nickname": "Tots",
    "Cool": "653",
    "Good": "300",
    "Bad": "27",
    "Miss": "47",
    "MaxCombo": "130",
    "Acc": "1.85%",
    "Progress": "F Rank",
    "Clear": "Failed",
    "PlayTime": "2022-12-02 00:24:14"
  },
  {
    "UserID": "72",
    "Nickname": "햇살",
    "Cool": "677",
    "Good": "268",
    "Bad": "6",
    "Miss": "51",
    "MaxCombo": "200",
    "Acc": "1.84%",
    "Progress": "F Rank",
    "Clear": "Failed",
    "PlayTime": "2022-09-23 23:00:51"
  },
  {
    "UserID": "6501",
    "Nickname": "dpn",
    "Cool": "684",
    "Good": "250",
    "Bad": "20",
    "Miss": "49",
    "MaxCombo": "122",
    "Acc": "1.81%",
    "Progress": "F Rank",
    "Clear": "Failed",
    "PlayTime": "2022-11-18 00:06:05"
  },
  {
    "UserID": "5456",
    "Nickname": "Load",
    "Cool": "724",
    "Good": "189",
    "Bad": "22",
    "Miss": "52",
    "MaxCombo": "131",
    "Acc": "1.77%",
    "Progress": "F Rank",
    "Clear": "Failed",
    "PlayTime": "2022-11-14 17:24:30"
  },
  {
    "UserID": "5543",
    "Nickname": "feesh",
    "Cool": "528",
    "Good": "308",
    "Bad": "25",
    "Miss": "45",
    "MaxCombo": "141",
    "Acc": "1.62%",
    "Progress": "F Rank",
    "Clear": "Failed",
    "PlayTime": "2022-09-14 23:30:11"
  },
  {
    "UserID": "5377",
    "Nickname": "o2jaaamE",
    "Cool": "341",
    "Good": "469",
    "Bad": "15",
    "Miss": "42",
    "MaxCombo": "96",
    "Acc": "1.57%",
    "Progress": "F Rank",
    "Clear": "Failed",
    "PlayTime": "2022-12-01 23:00:07"
  },
  {
    "UserID": "5447",
    "Nickname": "노스",
    "Cool": "514",
    "Good": "252",
    "Bad": "27",
    "Miss": "46",
    "MaxCombo": "99",
    "Acc": "1.49%",
    "Progress": "F Rank",
    "Clear": "Failed",
    "PlayTime": "2022-09-16 09:13:19"
  },
  {
    "UserID": "5357",
    "Nickname": "Lelloq",
    "Cool": "514",
    "Good": "180",
    "Bad": "22",
    "Miss": "42",
    "MaxCombo": "186",
    "Acc": "1.35%",
    "Progress": "F Rank",
    "Clear": "Failed",
    "PlayTime": "2022-09-15 03:19:08"
  },
  {
    "UserID": "5548",
    "Nickname": "clamati",
    "Cool": "566",
    "Good": "119",
    "Bad": "24",
    "Miss": "44",
    "MaxCombo": "157",
    "Acc": "1.33%",
    "Progress": "F Rank",
    "Clear": "Failed",
    "PlayTime": "2022-10-20 04:44:48"
  },
  {
    "UserID": "6437",
    "Nickname": "CharlyyyP",
    "Cool": "447",
    "Good": "222",
    "Bad": "16",
    "Miss": "43",
    "MaxCombo": "100",
    "Acc": "1.3%",
    "Progress": "F Rank",
    "Clear": "Failed",
    "PlayTime": "2022-09-11 18:40:37"
  },
  {
    "UserID": "5366",
    "Nickname": "VrChatGamer",
    "Cool": "442",
    "Good": "197",
    "Bad": "18",
    "Miss": "43",
    "MaxCombo": "84",
    "Acc": "1.24%",
    "Progress": "F Rank",
    "Clear": "Failed",
    "PlayTime": "2022-12-11 21:59:59"
  },
  {
    "UserID": "3328",
    "Nickname": "Ran",
    "Cool": "454",
    "Good": "182",
    "Bad": "14",
    "Miss": "42",
    "MaxCombo": "158",
    "Acc": "1.24%",
    "Progress": "F Rank",
    "Clear": "Failed",
    "PlayTime": "2022-10-14 23:30:32"
  },
  {
    "UserID": "6603",
    "Nickname": "Sorpy",
    "Cool": "326",
    "Good": "208",
    "Bad": "16",
    "Miss": "37",
    "MaxCombo": "162",
    "Acc": "1.04%",
    "Progress": "F Rank",
    "Clear": "Failed",
    "PlayTime": "2022-11-03 03:57:25"
  },
  {
    "UserID": "5551",
    "Nickname": "XiiaoRay",
    "Cool": "345",
    "Good": "170",
    "Bad": "10",
    "Miss": "42",
    "MaxCombo": "118",
    "Acc": "1.0%",
    "Progress": "F Rank",
    "Clear": "Failed",
    "PlayTime": "2022-09-14 23:30:11"
  },
  {
    "UserID": "5394",
    "Nickname": "Cypher",
    "Cool": "325",
    "Good": "187",
    "Bad": "0",
    "Miss": "40",
    "MaxCombo": "145",
    "Acc": "0.99%",
    "Progress": "F Rank",
    "Clear": "Failed",
    "PlayTime": "2022-11-15 22:51:25"
  },
  {
    "UserID": "2265",
    "Nickname": "제아롯드",
    "Cool": "267",
    "Good": "212",
    "Bad": "1",
    "Miss": "40",
    "MaxCombo": "101",
    "Acc": "0.93%",
    "Progress": "F Rank",
    "Clear": "Failed",
    "PlayTime": "2022-09-16 20:14:28"
  },
  {
    "UserID": "5944",
    "Nickname": "XaouXaou",
    "Cool": "261",
    "Good": "216",
    "Bad": "15",
    "Miss": "36",
    "MaxCombo": "152",
    "Acc": "0.93%",
    "Progress": "F Rank",
    "Clear": "Failed",
    "PlayTime": "2022-09-17 22:18:41"
  },
  {
    "UserID": "6265",
    "Nickname": "faz",
    "Cool": "404",
    "Good": "64",
    "Bad": "15",
    "Miss": "40",
    "MaxCombo": "135",
    "Acc": "0.91%",
    "Progress": "F Rank",
    "Clear": "Failed",
    "PlayTime": "2022-09-12 06:31:47"
  },
  {
    "UserID": "5780",
    "Nickname": "ririri",
    "Cool": "294",
    "Good": "167",
    "Bad": "5",
    "Miss": "43",
    "MaxCombo": "170",
    "Acc": "0.89%",
    "Progress": "F Rank",
    "Clear": "Failed",
    "PlayTime": "2022-10-16 22:07:31"
  },
  {
    "UserID": "5740",
    "Nickname": "DOG10DUK",
    "Cool": "321",
    "Good": "139",
    "Bad": "6",
    "Miss": "38",
    "MaxCombo": "170",
    "Acc": "0.89%",
    "Progress": "F Rank",
    "Clear": "Failed",
    "PlayTime": "2022-09-21 02:01:35"
  },
  {
    "UserID": "2233",
    "Nickname": "Bero",
    "Cool": "326",
    "Good": "131",
    "Bad": "0",
    "Miss": "40",
    "MaxCombo": "146",
    "Acc": "0.89%",
    "Progress": "F Rank",
    "Clear": "Failed",
    "PlayTime": "2022-09-25 20:37:47"
  },
  {
    "UserID": "16",
    "Nickname": "지존기병장장",
    "Cool": "263",
    "Good": "193",
    "Bad": "23",
    "Miss": "36",
    "MaxCombo": "93",
    "Acc": "0.88%",
    "Progress": "F Rank",
    "Clear": "Failed",
    "PlayTime": "2022-10-02 13:39:22"
  },
  {
    "UserID": "6053",
    "Nickname": "FakeException",
    "Cool": "327",
    "Good": "125",
    "Bad": "1",
    "Miss": "40",
    "MaxCombo": "160",
    "Acc": "0.88%",
    "Progress": "F Rank",
    "Clear": "Failed",
    "PlayTime": "2022-11-22 05:15:41"
  },
  {
    "UserID": "1191",
    "Nickname": "뉴비스",
    "Cool": "371",
    "Good": "80",
    "Bad": "23",
    "Miss": "37",
    "MaxCombo": "196",
    "Acc": "0.88%",
    "Progress": "F Rank",
    "Clear": "Failed",
    "PlayTime": "2022-09-14 20:09:43"
  },
  {
    "UserID": "6586",
    "Nickname": "Lovelyn",
    "Cool": "298",
    "Good": "146",
    "Bad": "8",
    "Miss": "39",
    "MaxCombo": "101",
    "Acc": "0.86%",
    "Progress": "F Rank",
    "Clear": "Failed",
    "PlayTime": "2022-10-10 02:11:42"
  },
  {
    "UserID": "6254",
    "Nickname": "CurlJam",
    "Cool": "373",
    "Good": "68",
    "Bad": "0",
    "Miss": "38",
    "MaxCombo": "265",
    "Acc": "0.86%",
    "Progress": "F Rank",
    "Clear": "Failed",
    "PlayTime": "2022-12-02 10:52:06"
  },
  {
    "UserID": "5822",
    "Nickname": "실존하는허수",
    "Cool": "304",
    "Good": "130",
    "Bad": "5",
    "Miss": "39",
    "MaxCombo": "149",
    "Acc": "0.84%",
    "Progress": "F Rank",
    "Clear": "Failed",
    "PlayTime": "2022-10-15 23:24:09"
  },
  {
    "UserID": "5897",
    "Nickname": "베키",
    "Cool": "306",
    "Good": "114",
    "Bad": "1",
    "Miss": "43",
    "MaxCombo": "107",
    "Acc": "0.82%",
    "Progress": "F Rank",
    "Clear": "Failed",
    "PlayTime": "2022-09-19 23:27:52"
  },
  {
    "UserID": "5640",
    "Nickname": "nohii",
    "Cool": "267",
    "Good": "150",
    "Bad": "12",
    "Miss": "40",
    "MaxCombo": "61",
    "Acc": "0.81%",
    "Progress": "F Rank",
    "Clear": "Failed",
    "PlayTime": "2022-09-19 23:27:52"
  },
  {
    "UserID": "5438",
    "Nickname": "sssmeguminsss",
    "Cool": "248",
    "Good": "148",
    "Bad": "23",
    "Miss": "36",
    "MaxCombo": "83",
    "Acc": "0.77%",
    "Progress": "F Rank",
    "Clear": "Failed",
    "PlayTime": "2022-10-06 22:10:06"
  },
  {
    "UserID": "6536",
    "Nickname": "sang981203",
    "Cool": "253",
    "Good": "133",
    "Bad": "14",
    "Miss": "38",
    "MaxCombo": "78",
    "Acc": "0.75%",
    "Progress": "F Rank",
    "Clear": "Failed",
    "PlayTime": "2022-10-11 23:07:48"
  },
  {
    "UserID": "1188",
    "Nickname": "Cuppp",
    "Cool": "271",
    "Good": "113",
    "Bad": "5",
    "Miss": "39",
    "MaxCombo": "137",
    "Acc": "0.75%",
    "Progress": "F Rank",
    "Clear": "Failed",
    "PlayTime": "2022-09-11 04:41:18"
  },
  {
    "UserID": "6597",
    "Nickname": "jangwook",
    "Cool": "239",
    "Good": "143",
    "Bad": "12",
    "Miss": "36",
    "MaxCombo": "99",
    "Acc": "0.74%",
    "Progress": "F Rank",
    "Clear": "Failed",
    "PlayTime": "2022-11-07 01:27:18"
  },
  {
    "UserID": "5677",
    "Nickname": "kimth",
    "Cool": "189",
    "Good": "179",
    "Bad": "12",
    "Miss": "37",
    "MaxCombo": "123",
    "Acc": "0.71%",
    "Progress": "F Rank",
    "Clear": "Failed",
    "PlayTime": "2022-12-06 14:18:20"
  },
  {
    "UserID": "5524",
    "Nickname": "Cheyn",
    "Cool": "203",
    "Good": "145",
    "Bad": "19",
    "Miss": "37",
    "MaxCombo": "47",
    "Acc": "0.68%",
    "Progress": "F Rank",
    "Clear": "Failed",
    "PlayTime": "2022-09-11 21:00:47"
  },
  {
    "UserID": "2289",
    "Nickname": "Emolga",
    "Cool": "237",
    "Good": "91",
    "Bad": "0",
    "Miss": "40",
    "MaxCombo": "96",
    "Acc": "0.64%",
    "Progress": "F Rank",
    "Clear": "Failed",
    "PlayTime": "2022-10-13 17:34:19"
  },
  {
    "UserID": "5628",
    "Nickname": "mgas",
    "Cool": "211",
    "Good": "111",
    "Bad": "4",
    "Miss": "38",
    "MaxCombo": "86",
    "Acc": "0.63%",
    "Progress": "F Rank",
    "Clear": "Failed",
    "PlayTime": "2022-09-11 07:44:30"
  },
  {
    "UserID": "6637",
    "Nickname": "피망",
    "Cool": "167",
    "Good": "154",
    "Bad": "1",
    "Miss": "39",
    "MaxCombo": "40",
    "Acc": "0.62%",
    "Progress": "F Rank",
    "Clear": "Failed",
    "PlayTime": "2022-12-04 22:54:29"
  },
  {
    "UserID": "5594",
    "Nickname": "예승이콩",
    "Cool": "176",
    "Good": "142",
    "Bad": "2",
    "Miss": "37",
    "MaxCombo": "155",
    "Acc": "0.62%",
    "Progress": "F Rank",
    "Clear": "Failed",
    "PlayTime": "2022-09-25 20:37:47"
  },
  {
    "UserID": "6530",
    "Nickname": "KAMATAYAN",
    "Cool": "194",
    "Good": "102",
    "Bad": "6",
    "Miss": "37",
    "MaxCombo": "87",
    "Acc": "0.57%",
    "Progress": "F Rank",
    "Clear": "Failed",
    "PlayTime": "2022-10-21 23:41:14"
  },
  {
    "UserID": "6565",
    "Nickname": "MysTic",
    "Cool": "210",
    "Good": "73",
    "Bad": "4",
    "Miss": "37",
    "MaxCombo": "102",
    "Acc": "0.55%",
    "Progress": "F Rank",
    "Clear": "Failed",
    "PlayTime": "2022-09-21 07:01:53"
  },
  {
    "UserID": "6050",
    "Nickname": "짬키",
    "Cool": "164",
    "Good": "61",
    "Bad": "3",
    "Miss": "35",
    "MaxCombo": "148",
    "Acc": "0.44%",
    "Progress": "F Rank",
    "Clear": "Failed",
    "PlayTime": "2022-10-11 22:54:13"
  },
  {
    "UserID": "6463",
    "Nickname": "mrking",
    "Cool": "138",
    "Good": "74",
    "Bad": "8",
    "Miss": "36",
    "MaxCombo": "60",
    "Acc": "0.41%",
    "Progress": "F Rank",
    "Clear": "Failed",
    "PlayTime": "2022-10-24 19:34:41"
  },
  {
    "UserID": "6391",
    "Nickname": "A2m",
    "Cool": "144",
    "Good": "48",
    "Bad": "10",
    "Miss": "36",
    "MaxCombo": "50",
    "Acc": "0.37%",
    "Progress": "F Rank",
    "Clear": "Failed",
    "PlayTime": "2022-10-03 00:56:58"
  },
  {
    "UserID": "5800",
    "Nickname": "-Victoria-",
    "Cool": "177",
    "Good": "14",
    "Bad": "1",
    "Miss": "38",
    "MaxCombo": "86",
    "Acc": "0.37%",
    "Progress": "F Rank",
    "Clear": "Failed",
    "PlayTime": "2022-11-09 03:32:39"
  },
  {
    "UserID": "6551",
    "Nickname": "Ransu",
    "Cool": "152",
    "Good": "28",
    "Bad": "0",
    "Miss": "37",
    "MaxCombo": "61",
    "Acc": "0.35%",
    "Progress": "F Rank",
    "Clear": "Failed",
    "PlayTime": "2022-09-14 03:00:49"
  },
  {
    "UserID": "6594",
    "Nickname": "YuJJun",
    "Cool": "127",
    "Good": "45",
    "Bad": "0",
    "Miss": "36",
    "MaxCombo": "67",
    "Acc": "0.33%",
    "Progress": "F Rank",
    "Clear": "Failed",
    "PlayTime": "2022-11-16 23:51:38"
  }
]