[
  {
    "UserID": "1166",
    "Nickname": "Delly.K",
    "Cool": "3086",
    "Good": "519",
    "Bad": "0",
    "Miss": "12",
    "MaxCombo": "1620",
    "Acc": "95.72%",
    "Progress": "A Rank",
    "Clear": "Cleared",
    "PlayTime": "2020-11-10 01:45:24"
  },
  {
    "UserID": "1202",
    "Nickname": "뜌",
    "Cool": "3016",
    "Good": "572",
    "Bad": "1",
    "Miss": "28",
    "MaxCombo": "755",
    "Acc": "91.36%",
    "Progress": "A Rank",
    "Clear": "Cleared",
    "PlayTime": "2020-11-10 01:45:24"
  },
  {
    "UserID": "152",
    "Nickname": "tomlee3",
    "Cool": "3241",
    "Good": "338",
    "Bad": "3",
    "Miss": "35",
    "MaxCombo": "1203",
    "Acc": "89.7%",
    "Progress": "B Rank",
    "Clear": "Cleared",
    "PlayTime": "2020-11-10 01:45:24"
  },
  {
    "UserID": "1173",
    "Nickname": "SuperPlay",
    "Cool": "2573",
    "Good": "1006",
    "Bad": "7",
    "Miss": "31",
    "MaxCombo": "1669",
    "Acc": "88.04%",
    "Progress": "B Rank",
    "Clear": "Cleared",
    "PlayTime": "2021-12-27 02:04:02"
  },
  {
    "UserID": "5561",
    "Nickname": "베리",
    "Cool": "3240",
    "Good": "332",
    "Bad": "0",
    "Miss": "45",
    "MaxCombo": "1350",
    "Acc": "87.98%",
    "Progress": "B Rank",
    "Clear": "Cleared",
    "PlayTime": "2021-07-04 23:01:16"
  },
  {
    "UserID": "1200",
    "Nickname": "무",
    "Cool": "2989",
    "Good": "585",
    "Bad": "3",
    "Miss": "40",
    "MaxCombo": "1065",
    "Acc": "87.84%",
    "Progress": "B Rank",
    "Clear": "Cleared",
    "PlayTime": "2020-11-10 01:45:24"
  },
  {
    "UserID": "5813",
    "Nickname": "스알",
    "Cool": "3109",
    "Good": "455",
    "Bad": "10",
    "Miss": "43",
    "MaxCombo": "691",
    "Acc": "85.68%",
    "Progress": "C Rank",
    "Clear": "Cleared",
    "PlayTime": "2021-11-27 17:08:25"
  },
  {
    "UserID": "4348",
    "Nickname": "nadavv",
    "Cool": "2666",
    "Good": "900",
    "Bad": "3",
    "Miss": "48",
    "MaxCombo": "689",
    "Acc": "85.07%",
    "Progress": "C Rank",
    "Clear": "Cleared",
    "PlayTime": "2022-01-20 08:22:15"
  },
  {
    "UserID": "5452",
    "Nickname": "ABC",
    "Cool": "3271",
    "Good": "288",
    "Bad": "1",
    "Miss": "57",
    "MaxCombo": "765",
    "Acc": "84.85%",
    "Progress": "C Rank",
    "Clear": "Cleared",
    "PlayTime": "2020-11-10 01:45:24"
  },
  {
    "UserID": "2237",
    "Nickname": "모모로",
    "Cool": "2927",
    "Good": "634",
    "Bad": "7",
    "Miss": "49",
    "MaxCombo": "1521",
    "Acc": "84.49%",
    "Progress": "C Rank",
    "Clear": "Cleared",
    "PlayTime": "2021-02-28 03:23:35"
  },
  {
    "UserID": "142",
    "Nickname": "SANDO",
    "Cool": "3089",
    "Good": "469",
    "Bad": "2",
    "Miss": "57",
    "MaxCombo": "1156",
    "Acc": "84.15%",
    "Progress": "C Rank",
    "Clear": "Cleared",
    "PlayTime": "2020-11-29 20:49:16"
  },
  {
    "UserID": "1207",
    "Nickname": "짬찌포병",
    "Cool": "2546",
    "Good": "1015",
    "Bad": "12",
    "Miss": "44",
    "MaxCombo": "767",
    "Acc": "83.54%",
    "Progress": "C Rank",
    "Clear": "Cleared",
    "PlayTime": "2021-02-02 01:15:18"
  },
  {
    "UserID": "85",
    "Nickname": "Royal777",
    "Cool": "3086",
    "Good": "469",
    "Bad": "0",
    "Miss": "62",
    "MaxCombo": "765",
    "Acc": "83.41%",
    "Progress": "C Rank",
    "Clear": "Cleared",
    "PlayTime": "2020-11-10 01:45:24"
  },
  {
    "UserID": "2260",
    "Nickname": "짜이우",
    "Cool": "3225",
    "Good": "326",
    "Bad": "1",
    "Miss": "65",
    "MaxCombo": "756",
    "Acc": "82.77%",
    "Progress": "C Rank",
    "Clear": "Cleared",
    "PlayTime": "2022-07-17 21:10:29"
  },
  {
    "UserID": "5358",
    "Nickname": "Cyubic",
    "Cool": "2751",
    "Good": "803",
    "Bad": "6",
    "Miss": "57",
    "MaxCombo": "1243",
    "Acc": "82.33%",
    "Progress": "C Rank",
    "Clear": "Cleared",
    "PlayTime": "2020-11-10 01:45:24"
  },
  {
    "UserID": "5713",
    "Nickname": "rorirocher",
    "Cool": "3080",
    "Good": "466",
    "Bad": "0",
    "Miss": "71",
    "MaxCombo": "756",
    "Acc": "81.17%",
    "Progress": "C Rank",
    "Clear": "Cleared",
    "PlayTime": "2021-07-04 23:01:16"
  },
  {
    "UserID": "5359",
    "Nickname": "WaKa",
    "Cool": "2698",
    "Good": "849",
    "Bad": "1",
    "Miss": "69",
    "MaxCombo": "758",
    "Acc": "80.47%",
    "Progress": "C Rank",
    "Clear": "Cleared",
    "PlayTime": "2020-11-10 01:45:24"
  },
  {
    "UserID": "141",
    "Nickname": "침묵",
    "Cool": "3163",
    "Good": "378",
    "Bad": "0",
    "Miss": "76",
    "MaxCombo": "756",
    "Acc": "80.15%",
    "Progress": "C Rank",
    "Clear": "Cleared",
    "PlayTime": "2021-01-05 21:57:47"
  },
  {
    "UserID": "4326",
    "Nickname": "BananenTropfen",
    "Cool": "2956",
    "Good": "587",
    "Bad": "6",
    "Miss": "68",
    "MaxCombo": "377",
    "Acc": "80.13%",
    "Progress": "C Rank",
    "Clear": "Cleared",
    "PlayTime": "2022-02-02 01:13:57"
  },
  {
    "UserID": "165",
    "Nickname": "Chess",
    "Cool": "2878",
    "Good": "665",
    "Bad": "25",
    "Miss": "49",
    "MaxCombo": "1083",
    "Acc": "79.93%",
    "Progress": "C Rank",
    "Clear": "Cleared",
    "PlayTime": "2022-07-08 15:38:34"
  },
  {
    "UserID": "2279",
    "Nickname": "dadots123",
    "Cool": "3080",
    "Good": "460",
    "Bad": "3",
    "Miss": "74",
    "MaxCombo": "766",
    "Acc": "79.7%",
    "Progress": "C Rank",
    "Clear": "Cleared",
    "PlayTime": "2022-11-09 21:50:03"
  },
  {
    "UserID": "2272",
    "Nickname": "skswkd",
    "Cool": "2905",
    "Good": "634",
    "Bad": "16",
    "Miss": "62",
    "MaxCombo": "778",
    "Acc": "79.01%",
    "Progress": "C Rank",
    "Clear": "Cleared",
    "PlayTime": "2020-11-10 01:45:24"
  },
  {
    "UserID": "3335",
    "Nickname": "gero",
    "Cool": "2986",
    "Good": "549",
    "Bad": "20",
    "Miss": "62",
    "MaxCombo": "725",
    "Acc": "78.23%",
    "Progress": "C Rank",
    "Clear": "Cleared",
    "PlayTime": "2022-06-24 16:29:36"
  },
  {
    "UserID": "41",
    "Nickname": "Chords",
    "Cool": "2886",
    "Good": "646",
    "Bad": "10",
    "Miss": "75",
    "MaxCombo": "752",
    "Acc": "77.24%",
    "Progress": "D Rank",
    "Clear": "Cleared",
    "PlayTime": "2020-11-10 01:45:24"
  },
  {
    "UserID": "1181",
    "Nickname": "못하는톰",
    "Cool": "2000",
    "Good": "1539",
    "Bad": "28",
    "Miss": "50",
    "MaxCombo": "765",
    "Acc": "76.76%",
    "Progress": "D Rank",
    "Clear": "Cleared",
    "PlayTime": "2020-11-10 01:45:24"
  },
  {
    "UserID": "5822",
    "Nickname": "실존하는허수",
    "Cool": "2988",
    "Good": "540",
    "Bad": "25",
    "Miss": "64",
    "MaxCombo": "1071",
    "Acc": "76.51%",
    "Progress": "D Rank",
    "Clear": "Cleared",
    "PlayTime": "2022-01-21 19:04:14"
  },
  {
    "UserID": "2262",
    "Nickname": "Wizard",
    "Cool": "2645",
    "Good": "886",
    "Bad": "24",
    "Miss": "62",
    "MaxCombo": "758",
    "Acc": "76.4%",
    "Progress": "D Rank",
    "Clear": "Cleared",
    "PlayTime": "2021-05-22 17:56:48"
  },
  {
    "UserID": "5428",
    "Nickname": "푸푸민우",
    "Cool": "2555",
    "Good": "974",
    "Bad": "19",
    "Miss": "69",
    "MaxCombo": "470",
    "Acc": "75.68%",
    "Progress": "D Rank",
    "Clear": "Cleared",
    "PlayTime": "2022-07-08 15:38:34"
  },
  {
    "UserID": "1204",
    "Nickname": "거미",
    "Cool": "2906",
    "Good": "613",
    "Bad": "13",
    "Miss": "85",
    "MaxCombo": "699",
    "Acc": "74.09%",
    "Progress": "D Rank",
    "Clear": "Cleared",
    "PlayTime": "2021-01-26 19:46:20"
  },
  {
    "UserID": "5637",
    "Nickname": "corenik",
    "Cool": "2814",
    "Good": "705",
    "Bad": "13",
    "Miss": "85",
    "MaxCombo": "740",
    "Acc": "73.86%",
    "Progress": "D Rank",
    "Clear": "Cleared",
    "PlayTime": "2021-03-04 23:03:35"
  },
  {
    "UserID": "5365",
    "Nickname": "LaserMan",
    "Cool": "2775",
    "Good": "742",
    "Bad": "15",
    "Miss": "85",
    "MaxCombo": "761",
    "Acc": "73.27%",
    "Progress": "D Rank",
    "Clear": "Cleared",
    "PlayTime": "2021-07-28 18:11:40"
  },
  {
    "UserID": "5827",
    "Nickname": "워너비",
    "Cool": "2950",
    "Good": "564",
    "Bad": "32",
    "Miss": "71",
    "MaxCombo": "389",
    "Acc": "72.97%",
    "Progress": "D Rank",
    "Clear": "Cleared",
    "PlayTime": "2022-10-15 21:04:46"
  },
  {
    "UserID": "4334",
    "Nickname": "zimcasts",
    "Cool": "2839",
    "Good": "675",
    "Bad": "19",
    "Miss": "84",
    "MaxCombo": "768",
    "Acc": "72.69%",
    "Progress": "D Rank",
    "Clear": "Cleared",
    "PlayTime": "2021-02-23 19:48:45"
  },
  {
    "UserID": "5633",
    "Nickname": "LL",
    "Cool": "2999",
    "Good": "513",
    "Bad": "3",
    "Miss": "102",
    "MaxCombo": "454",
    "Acc": "72.6%",
    "Progress": "D Rank",
    "Clear": "Cleared",
    "PlayTime": "2021-03-10 22:57:24"
  },
  {
    "UserID": "5438",
    "Nickname": "sssmeguminsss",
    "Cool": "2777",
    "Good": "732",
    "Bad": "28",
    "Miss": "80",
    "MaxCombo": "689",
    "Acc": "71.31%",
    "Progress": "D Rank",
    "Clear": "Cleared",
    "PlayTime": "2022-08-17 22:35:45"
  },
  {
    "UserID": "3328",
    "Nickname": "Ran",
    "Cool": "3020",
    "Good": "486",
    "Bad": "9",
    "Miss": "102",
    "MaxCombo": "390",
    "Acc": "71.17%",
    "Progress": "D Rank",
    "Clear": "Cleared",
    "PlayTime": "2022-12-09 06:28:24"
  },
  {
    "UserID": "5780",
    "Nickname": "ririri",
    "Cool": "2690",
    "Good": "819",
    "Bad": "32",
    "Miss": "76",
    "MaxCombo": "522",
    "Acc": "71.09%",
    "Progress": "D Rank",
    "Clear": "Cleared",
    "PlayTime": "2022-01-13 23:41:49"
  },
  {
    "UserID": "5550",
    "Nickname": "Meow",
    "Cool": "2757",
    "Good": "750",
    "Bad": "37",
    "Miss": "73",
    "MaxCombo": "1071",
    "Acc": "70.76%",
    "Progress": "D Rank",
    "Clear": "Cleared",
    "PlayTime": "2020-11-10 01:45:24"
  },
  {
    "UserID": "6080",
    "Nickname": "Mmg",
    "Cool": "2800",
    "Good": "705",
    "Bad": "15",
    "Miss": "97",
    "MaxCombo": "433",
    "Acc": "70.38%",
    "Progress": "D Rank",
    "Clear": "Cleared",
    "PlayTime": "2021-05-24 01:48:09"
  },
  {
    "UserID": "1225",
    "Nickname": "Bazzi",
    "Cool": "2645",
    "Good": "859",
    "Bad": "27",
    "Miss": "86",
    "MaxCombo": "462",
    "Acc": "69.75%",
    "Progress": "D Rank",
    "Clear": "Cleared",
    "PlayTime": "2022-09-03 18:54:30"
  },
  {
    "UserID": "6141",
    "Nickname": "XinYang",
    "Cool": "1957",
    "Good": "1553",
    "Bad": "34",
    "Miss": "73",
    "MaxCombo": "513",
    "Acc": "69.51%",
    "Progress": "D Rank",
    "Clear": "Cleared",
    "PlayTime": "2021-07-11 18:04:23"
  },
  {
    "UserID": "5632",
    "Nickname": "TT",
    "Cool": "2409",
    "Good": "1091",
    "Bad": "38",
    "Miss": "79",
    "MaxCombo": "521",
    "Acc": "68.17%",
    "Progress": "D Rank",
    "Clear": "Cleared",
    "PlayTime": "2021-04-29 23:07:15"
  },
  {
    "UserID": "2266",
    "Nickname": "료슬",
    "Cool": "2849",
    "Good": "642",
    "Bad": "32",
    "Miss": "94",
    "MaxCombo": "760",
    "Acc": "67.05%",
    "Progress": "D Rank",
    "Clear": "Cleared",
    "PlayTime": "2020-11-10 01:45:24"
  },
  {
    "UserID": "5929",
    "Nickname": "Azrael",
    "Cool": "3142",
    "Good": "389",
    "Bad": "5",
    "Miss": "76",
    "MaxCombo": "757",
    "Acc": "62.11%",
    "Progress": "D Rank",
    "Clear": "Failed",
    "PlayTime": "2021-03-25 16:38:27"
  },
  {
    "UserID": "6335",
    "Nickname": "시아",
    "Cool": "2315",
    "Good": "1224",
    "Bad": "5",
    "Miss": "66",
    "MaxCombo": "779",
    "Acc": "62.04%",
    "Progress": "D Rank",
    "Clear": "Failed",
    "PlayTime": "2021-12-15 23:07:55"
  },
  {
    "UserID": "5821",
    "Nickname": "NewsTimeK",
    "Cool": "2854",
    "Good": "667",
    "Bad": "4",
    "Miss": "85",
    "MaxCombo": "756",
    "Acc": "59.56%",
    "Progress": "D Rank",
    "Clear": "Failed",
    "PlayTime": "2021-10-05 23:11:26"
  },
  {
    "UserID": "2328",
    "Nickname": "★Kakuri",
    "Cool": "2607",
    "Good": "916",
    "Bad": "0",
    "Miss": "87",
    "MaxCombo": "675",
    "Acc": "59.46%",
    "Progress": "D Rank",
    "Clear": "Failed",
    "PlayTime": "2021-08-11 00:12:25"
  },
  {
    "UserID": "2263",
    "Nickname": "Eve",
    "Cool": "2544",
    "Good": "969",
    "Bad": "17",
    "Miss": "78",
    "MaxCombo": "972",
    "Acc": "57.37%",
    "Progress": "D Rank",
    "Clear": "Failed",
    "PlayTime": "2022-02-25 21:51:54"
  },
  {
    "UserID": "2265",
    "Nickname": "제아롯드",
    "Cool": "3001",
    "Good": "506",
    "Bad": "4",
    "Miss": "101",
    "MaxCombo": "383",
    "Acc": "57.1%",
    "Progress": "D Rank",
    "Clear": "Failed",
    "PlayTime": "2022-01-28 21:12:45"
  },
  {
    "UserID": "2233",
    "Nickname": "Bero",
    "Cool": "2896",
    "Good": "612",
    "Bad": "5",
    "Miss": "83",
    "MaxCombo": "494",
    "Acc": "57.08%",
    "Progress": "D Rank",
    "Clear": "Failed",
    "PlayTime": "2022-03-30 00:34:44"
  },
  {
    "UserID": "5620",
    "Nickname": "Niggy",
    "Cool": "2957",
    "Good": "546",
    "Bad": "7",
    "Miss": "100",
    "MaxCombo": "763",
    "Acc": "56.22%",
    "Progress": "D Rank",
    "Clear": "Failed",
    "PlayTime": "2021-03-31 21:00:03"
  },
  {
    "UserID": "5377",
    "Nickname": "o2jaaamE",
    "Cool": "2672",
    "Good": "833",
    "Bad": "15",
    "Miss": "89",
    "MaxCombo": "765",
    "Acc": "56.05%",
    "Progress": "D Rank",
    "Clear": "Failed",
    "PlayTime": "2021-02-02 01:15:18"
  },
  {
    "UserID": "6081",
    "Nickname": "Daipeng",
    "Cool": "2760",
    "Good": "744",
    "Bad": "13",
    "Miss": "90",
    "MaxCombo": "758",
    "Acc": "56.03%",
    "Progress": "D Rank",
    "Clear": "Failed",
    "PlayTime": "2021-07-11 18:04:23"
  },
  {
    "UserID": "6501",
    "Nickname": "dpn",
    "Cool": "2981",
    "Good": "519",
    "Bad": "5",
    "Miss": "105",
    "MaxCombo": "544",
    "Acc": "55.68%",
    "Progress": "D Rank",
    "Clear": "Failed",
    "PlayTime": "2022-11-13 07:05:59"
  },
  {
    "UserID": "130",
    "Nickname": "모기",
    "Cool": "2782",
    "Good": "719",
    "Bad": "23",
    "Miss": "88",
    "MaxCombo": "468",
    "Acc": "55.48%",
    "Progress": "D Rank",
    "Clear": "Failed",
    "PlayTime": "2022-01-29 14:13:19"
  },
  {
    "UserID": "2300",
    "Nickname": "그림자",
    "Cool": "2957",
    "Good": "540",
    "Bad": "12",
    "Miss": "97",
    "MaxCombo": "427",
    "Acc": "55.04%",
    "Progress": "D Rank",
    "Clear": "Failed",
    "PlayTime": "2022-10-14 00:54:18"
  },
  {
    "UserID": "5740",
    "Nickname": "DOG10DUK",
    "Cool": "2830",
    "Good": "664",
    "Bad": "18",
    "Miss": "95",
    "MaxCombo": "745",
    "Acc": "54.19%",
    "Progress": "D Rank",
    "Clear": "Failed",
    "PlayTime": "2021-05-24 00:16:38"
  },
  {
    "UserID": "1191",
    "Nickname": "뉴비스",
    "Cool": "2873",
    "Good": "620",
    "Bad": "11",
    "Miss": "101",
    "MaxCombo": "643",
    "Acc": "54.08%",
    "Progress": "D Rank",
    "Clear": "Failed",
    "PlayTime": "2022-06-08 23:50:38"
  },
  {
    "UserID": "2283",
    "Nickname": "Aili",
    "Cool": "2839",
    "Good": "652",
    "Bad": "10",
    "Miss": "99",
    "MaxCombo": "744",
    "Acc": "53.62%",
    "Progress": "D Rank",
    "Clear": "Failed",
    "PlayTime": "2022-03-30 19:34:47"
  },
  {
    "UserID": "5577",
    "Nickname": "Sweetsoul",
    "Cool": "2892",
    "Good": "598",
    "Bad": "2",
    "Miss": "106",
    "MaxCombo": "756",
    "Acc": "53.53%",
    "Progress": "D Rank",
    "Clear": "Failed",
    "PlayTime": "2022-10-16 20:33:18"
  },
  {
    "UserID": "6025",
    "Nickname": "넨시",
    "Cool": "2848",
    "Good": "642",
    "Bad": "20",
    "Miss": "90",
    "MaxCombo": "1069",
    "Acc": "53.44%",
    "Progress": "D Rank",
    "Clear": "Failed",
    "PlayTime": "2022-11-25 22:07:35"
  },
  {
    "UserID": "5673",
    "Nickname": "allen poknat",
    "Cool": "2822",
    "Good": "667",
    "Bad": "5",
    "Miss": "103",
    "MaxCombo": "754",
    "Acc": "53.19%",
    "Progress": "D Rank",
    "Clear": "Failed",
    "PlayTime": "2021-03-04 23:03:35"
  },
  {
    "UserID": "5621",
    "Nickname": "Deneb",
    "Cool": "2941",
    "Good": "546",
    "Bad": "14",
    "Miss": "102",
    "MaxCombo": "493",
    "Acc": "53.04%",
    "Progress": "D Rank",
    "Clear": "Failed",
    "PlayTime": "2021-05-11 22:42:34"
  },
  {
    "UserID": "2257",
    "Nickname": "LunaticAnt",
    "Cool": "2840",
    "Good": "648",
    "Bad": "21",
    "Miss": "89",
    "MaxCombo": "487",
    "Acc": "53.03%",
    "Progress": "D Rank",
    "Clear": "Failed",
    "PlayTime": "2021-06-04 22:08:00"
  },
  {
    "UserID": "5464",
    "Nickname": "DumbFunk",
    "Cool": "2462",
    "Good": "1029",
    "Bad": "29",
    "Miss": "80",
    "MaxCombo": "767",
    "Acc": "52.87%",
    "Progress": "D Rank",
    "Clear": "Failed",
    "PlayTime": "2020-11-10 01:45:24"
  },
  {
    "UserID": "5431",
    "Nickname": "SSU",
    "Cool": "2931",
    "Good": "553",
    "Bad": "25",
    "Miss": "93",
    "MaxCombo": "757",
    "Acc": "52.42%",
    "Progress": "D Rank",
    "Clear": "Failed",
    "PlayTime": "2022-04-29 21:54:48"
  },
  {
    "UserID": "2301",
    "Nickname": "Midnight",
    "Cool": "2644",
    "Good": "835",
    "Bad": "11",
    "Miss": "95",
    "MaxCombo": "423",
    "Acc": "50.87%",
    "Progress": "D Rank",
    "Clear": "Failed",
    "PlayTime": "2020-11-10 01:45:24"
  },
  {
    "UserID": "6052",
    "Nickname": "Wubby",
    "Cool": "2674",
    "Good": "801",
    "Bad": "48",
    "Miss": "82",
    "MaxCombo": "564",
    "Acc": "50.14%",
    "Progress": "D Rank",
    "Clear": "Failed",
    "PlayTime": "2022-06-15 23:17:57"
  },
  {
    "UserID": "5407",
    "Nickname": "안다로미",
    "Cool": "2847",
    "Good": "618",
    "Bad": "48",
    "Miss": "96",
    "MaxCombo": "599",
    "Acc": "48.51%",
    "Progress": "F Rank",
    "Clear": "Failed",
    "PlayTime": "2022-08-04 00:20:59"
  },
  {
    "UserID": "2312",
    "Nickname": "VFB",
    "Cool": "2658",
    "Good": "808",
    "Bad": "37",
    "Miss": "95",
    "MaxCombo": "403",
    "Acc": "48.33%",
    "Progress": "F Rank",
    "Clear": "Failed",
    "PlayTime": "2020-11-10 01:45:24"
  },
  {
    "UserID": "2309",
    "Nickname": "Yuel",
    "Cool": "2871",
    "Good": "590",
    "Bad": "27",
    "Miss": "98",
    "MaxCombo": "699",
    "Acc": "47.77%",
    "Progress": "F Rank",
    "Clear": "Failed",
    "PlayTime": "2021-05-09 00:28:52"
  },
  {
    "UserID": "5687",
    "Nickname": "CreamyKipay",
    "Cool": "2812",
    "Good": "649",
    "Bad": "4",
    "Miss": "98",
    "MaxCombo": "752",
    "Acc": "47.65%",
    "Progress": "F Rank",
    "Clear": "Failed",
    "PlayTime": "2022-06-02 22:57:25"
  },
  {
    "UserID": "6452",
    "Nickname": "Ayam88",
    "Cool": "2835",
    "Good": "621",
    "Bad": "30",
    "Miss": "96",
    "MaxCombo": "592",
    "Acc": "46.72%",
    "Progress": "F Rank",
    "Clear": "Failed",
    "PlayTime": "2022-06-16 22:23:19"
  },
  {
    "UserID": "5724",
    "Nickname": "번지",
    "Cool": "2903",
    "Good": "536",
    "Bad": "26",
    "Miss": "99",
    "MaxCombo": "304",
    "Acc": "43.5%",
    "Progress": "F Rank",
    "Clear": "Failed",
    "PlayTime": "2021-05-05 13:46:52"
  },
  {
    "UserID": "5968",
    "Nickname": "adas",
    "Cool": "2604",
    "Good": "829",
    "Bad": "16",
    "Miss": "91",
    "MaxCombo": "392",
    "Acc": "41.72%",
    "Progress": "F Rank",
    "Clear": "Failed",
    "PlayTime": "2022-08-31 01:30:09"
  },
  {
    "UserID": "1228",
    "Nickname": "11th",
    "Cool": "2686",
    "Good": "743",
    "Bad": "19",
    "Miss": "97",
    "MaxCombo": "365",
    "Acc": "41.1%",
    "Progress": "F Rank",
    "Clear": "Failed",
    "PlayTime": "2022-02-09 21:52:49"
  },
  {
    "UserID": "2306",
    "Nickname": "metyabo",
    "Cool": "2973",
    "Good": "437",
    "Bad": "14",
    "Miss": "104",
    "MaxCombo": "354",
    "Acc": "37.92%",
    "Progress": "F Rank",
    "Clear": "Failed",
    "PlayTime": "2020-11-10 01:45:24"
  },
  {
    "UserID": "5364",
    "Nickname": "페카",
    "Cool": "2745",
    "Good": "662",
    "Bad": "29",
    "Miss": "80",
    "MaxCombo": "756",
    "Acc": "36.88%",
    "Progress": "F Rank",
    "Clear": "Failed",
    "PlayTime": "2022-01-20 21:00:33"
  },
  {
    "UserID": "6082",
    "Nickname": "DBcooper",
    "Cool": "2527",
    "Good": "879",
    "Bad": "42",
    "Miss": "88",
    "MaxCombo": "495",
    "Acc": "36.25%",
    "Progress": "F Rank",
    "Clear": "Failed",
    "PlayTime": "2021-05-26 03:11:18"
  },
  {
    "UserID": "43",
    "Nickname": "BS",
    "Cool": "2581",
    "Good": "737",
    "Bad": "24",
    "Miss": "98",
    "MaxCombo": "424",
    "Acc": "19.01%",
    "Progress": "F Rank",
    "Clear": "Failed",
    "PlayTime": "2020-11-10 01:45:24"
  },
  {
    "UserID": "5794",
    "Nickname": "권승",
    "Cool": "2762",
    "Good": "538",
    "Bad": "25",
    "Miss": "96",
    "MaxCombo": "751",
    "Acc": "15.83%",
    "Progress": "F Rank",
    "Clear": "Failed",
    "PlayTime": "2021-01-09 23:15:02"
  },
  {
    "UserID": "5931",
    "Nickname": "Xyphoes",
    "Cool": "2746",
    "Good": "531",
    "Bad": "24",
    "Miss": "96",
    "MaxCombo": "726",
    "Acc": "11.26%",
    "Progress": "F Rank",
    "Clear": "Failed",
    "PlayTime": "2021-08-01 22:53:12"
  },
  {
    "UserID": "5897",
    "Nickname": "베키",
    "Cool": "2652",
    "Good": "623",
    "Bad": "35",
    "Miss": "90",
    "MaxCombo": "757",
    "Acc": "10.68%",
    "Progress": "F Rank",
    "Clear": "Failed",
    "PlayTime": "2022-06-14 00:50:39"
  },
  {
    "UserID": "5600",
    "Nickname": "코스모스",
    "Cool": "2643",
    "Good": "630",
    "Bad": "10",
    "Miss": "97",
    "MaxCombo": "755",
    "Acc": "10.27%",
    "Progress": "F Rank",
    "Clear": "Failed",
    "PlayTime": "2022-05-18 13:45:05"
  },
  {
    "UserID": "5356",
    "Nickname": "Paprotka",
    "Cool": "2762",
    "Good": "507",
    "Bad": "29",
    "Miss": "101",
    "MaxCombo": "391",
    "Acc": "9.72%",
    "Progress": "F Rank",
    "Clear": "Failed",
    "PlayTime": "2021-08-16 01:33:47"
  },
  {
    "UserID": "2289",
    "Nickname": "Emolga",
    "Cool": "2808",
    "Good": "460",
    "Bad": "16",
    "Miss": "99",
    "MaxCombo": "756",
    "Acc": "9.61%",
    "Progress": "F Rank",
    "Clear": "Failed",
    "PlayTime": "2021-08-09 22:38:46"
  },
  {
    "UserID": "5730",
    "Nickname": "IrritableTing",
    "Cool": "2770",
    "Good": "492",
    "Bad": "14",
    "Miss": "101",
    "MaxCombo": "564",
    "Acc": "8.35%",
    "Progress": "F Rank",
    "Clear": "Failed",
    "PlayTime": "2021-04-21 21:05:28"
  },
  {
    "UserID": "5714",
    "Nickname": "아린",
    "Cool": "2141",
    "Good": "1113",
    "Bad": "54",
    "Miss": "84",
    "MaxCombo": "319",
    "Acc": "7.97%",
    "Progress": "F Rank",
    "Clear": "Failed",
    "PlayTime": "2022-12-01 05:14:21"
  },
  {
    "UserID": "6242",
    "Nickname": "Jfritz",
    "Cool": "2570",
    "Good": "660",
    "Bad": "19",
    "Miss": "100",
    "MaxCombo": "431",
    "Acc": "7.92%",
    "Progress": "F Rank",
    "Clear": "Failed",
    "PlayTime": "2022-08-19 20:06:46"
  },
  {
    "UserID": "5607",
    "Nickname": "Aryan",
    "Cool": "2222",
    "Good": "1011",
    "Bad": "41",
    "Miss": "90",
    "MaxCombo": "369",
    "Acc": "7.92%",
    "Progress": "F Rank",
    "Clear": "Failed",
    "PlayTime": "2020-11-10 01:45:24"
  },
  {
    "UserID": "5412",
    "Nickname": "물오리",
    "Cool": "2588",
    "Good": "640",
    "Bad": "23",
    "Miss": "101",
    "MaxCombo": "321",
    "Acc": "7.92%",
    "Progress": "F Rank",
    "Clear": "Failed",
    "PlayTime": "2021-05-07 17:55:03"
  },
  {
    "UserID": "5745",
    "Nickname": "Alexiel",
    "Cool": "2427",
    "Good": "791",
    "Bad": "10",
    "Miss": "94",
    "MaxCombo": "416",
    "Acc": "7.89%",
    "Progress": "F Rank",
    "Clear": "Failed",
    "PlayTime": "2022-05-18 18:43:50"
  },
  {
    "UserID": "5944",
    "Nickname": "XaouXaou",
    "Cool": "2194",
    "Good": "1018",
    "Bad": "30",
    "Miss": "89",
    "MaxCombo": "513",
    "Acc": "7.87%",
    "Progress": "F Rank",
    "Clear": "Failed",
    "PlayTime": "2022-04-14 16:49:10"
  },
  {
    "UserID": "5367",
    "Nickname": "rlarkgus",
    "Cool": "2462",
    "Good": "745",
    "Bad": "17",
    "Miss": "90",
    "MaxCombo": "498",
    "Acc": "7.86%",
    "Progress": "F Rank",
    "Clear": "Failed",
    "PlayTime": "2020-11-10 01:45:24"
  },
  {
    "UserID": "5732",
    "Nickname": "Loligod",
    "Cool": "2329",
    "Good": "877",
    "Bad": "30",
    "Miss": "86",
    "MaxCombo": "643",
    "Acc": "7.86%",
    "Progress": "F Rank",
    "Clear": "Failed",
    "PlayTime": "2022-09-16 20:51:15"
  },
  {
    "UserID": "5735",
    "Nickname": "shaafs",
    "Cool": "2663",
    "Good": "531",
    "Bad": "15",
    "Miss": "96",
    "MaxCombo": "496",
    "Acc": "7.84%",
    "Progress": "F Rank",
    "Clear": "Failed",
    "PlayTime": "2022-02-05 23:35:39"
  },
  {
    "UserID": "5760",
    "Nickname": "invijoss",
    "Cool": "2319",
    "Good": "872",
    "Bad": "52",
    "Miss": "80",
    "MaxCombo": "362",
    "Acc": "7.82%",
    "Progress": "F Rank",
    "Clear": "Failed",
    "PlayTime": "2022-08-01 16:58:53"
  },
  {
    "UserID": "6008",
    "Nickname": "Guodan",
    "Cool": "2354",
    "Good": "828",
    "Bad": "33",
    "Miss": "91",
    "MaxCombo": "448",
    "Acc": "7.8%",
    "Progress": "F Rank",
    "Clear": "Failed",
    "PlayTime": "2021-03-25 16:38:27"
  },
  {
    "UserID": "5372",
    "Nickname": "사람임",
    "Cool": "2479",
    "Good": "693",
    "Bad": "25",
    "Miss": "96",
    "MaxCombo": "481",
    "Acc": "7.78%",
    "Progress": "F Rank",
    "Clear": "Failed",
    "PlayTime": "2022-07-04 18:52:28"
  },
  {
    "UserID": "5357",
    "Nickname": "Lelloq",
    "Cool": "2670",
    "Good": "494",
    "Bad": "13",
    "Miss": "99",
    "MaxCombo": "354",
    "Acc": "7.76%",
    "Progress": "F Rank",
    "Clear": "Failed",
    "PlayTime": "2020-11-10 01:45:24"
  },
  {
    "UserID": "6463",
    "Nickname": "mrking",
    "Cool": "2079",
    "Good": "1077",
    "Bad": "38",
    "Miss": "77",
    "MaxCombo": "445",
    "Acc": "7.73%",
    "Progress": "F Rank",
    "Clear": "Failed",
    "PlayTime": "2022-11-02 02:17:42"
  },
  {
    "UserID": "2304",
    "Nickname": "Asta`Kun",
    "Cool": "2342",
    "Good": "764",
    "Bad": "37",
    "Miss": "85",
    "MaxCombo": "508",
    "Acc": "7.61%",
    "Progress": "F Rank",
    "Clear": "Failed",
    "PlayTime": "2020-11-10 01:45:24"
  },
  {
    "UserID": "5906",
    "Nickname": "arima",
    "Cool": "2137",
    "Good": "927",
    "Bad": "28",
    "Miss": "83",
    "MaxCombo": "676",
    "Acc": "7.51%",
    "Progress": "F Rank",
    "Clear": "Failed",
    "PlayTime": "2021-03-22 20:13:14"
  },
  {
    "UserID": "5942",
    "Nickname": "JOKER",
    "Cool": "2643",
    "Good": "384",
    "Bad": "14",
    "Miss": "98",
    "MaxCombo": "538",
    "Acc": "7.43%",
    "Progress": "F Rank",
    "Clear": "Failed",
    "PlayTime": "2021-05-01 15:41:51"
  },
  {
    "UserID": "5540",
    "Nickname": "Enter",
    "Cool": "2456",
    "Good": "563",
    "Bad": "31",
    "Miss": "86",
    "MaxCombo": "489",
    "Acc": "7.41%",
    "Progress": "F Rank",
    "Clear": "Failed",
    "PlayTime": "2020-11-10 01:45:24"
  },
  {
    "UserID": "6093",
    "Nickname": "Kenth",
    "Cool": "2244",
    "Good": "761",
    "Bad": "29",
    "Miss": "88",
    "MaxCombo": "359",
    "Acc": "7.37%",
    "Progress": "F Rank",
    "Clear": "Failed",
    "PlayTime": "2022-02-16 03:20:46"
  },
  {
    "UserID": "1188",
    "Nickname": "Cuppp",
    "Cool": "2348",
    "Good": "642",
    "Bad": "5",
    "Miss": "92",
    "MaxCombo": "414",
    "Acc": "7.33%",
    "Progress": "F Rank",
    "Clear": "Failed",
    "PlayTime": "2022-08-22 02:46:59"
  },
  {
    "UserID": "6443",
    "Nickname": "Milla",
    "Cool": "2506",
    "Good": "437",
    "Bad": "5",
    "Miss": "97",
    "MaxCombo": "352",
    "Acc": "7.22%",
    "Progress": "F Rank",
    "Clear": "Failed",
    "PlayTime": "2022-08-24 00:09:43"
  },
  {
    "UserID": "5352",
    "Nickname": "Ravile",
    "Cool": "2299",
    "Good": "637",
    "Bad": "19",
    "Miss": "85",
    "MaxCombo": "754",
    "Acc": "7.2%",
    "Progress": "F Rank",
    "Clear": "Failed",
    "PlayTime": "2020-11-10 01:45:24"
  },
  {
    "UserID": "5468",
    "Nickname": "choichan",
    "Cool": "2156",
    "Good": "773",
    "Bad": "18",
    "Miss": "87",
    "MaxCombo": "384",
    "Acc": "7.18%",
    "Progress": "F Rank",
    "Clear": "Failed",
    "PlayTime": "2022-11-22 21:15:34"
  },
  {
    "UserID": "5447",
    "Nickname": "노스",
    "Cool": "2371",
    "Good": "554",
    "Bad": "27",
    "Miss": "89",
    "MaxCombo": "381",
    "Acc": "7.17%",
    "Progress": "F Rank",
    "Clear": "Failed",
    "PlayTime": "2022-06-08 23:05:42"
  },
  {
    "UserID": "5398",
    "Nickname": "Sariel",
    "Cool": "2486",
    "Good": "418",
    "Bad": "4",
    "Miss": "99",
    "MaxCombo": "272",
    "Acc": "7.13%",
    "Progress": "F Rank",
    "Clear": "Failed",
    "PlayTime": "2020-11-10 01:45:24"
  },
  {
    "UserID": "5836",
    "Nickname": "Kei-",
    "Cool": "2562",
    "Good": "339",
    "Bad": "5",
    "Miss": "92",
    "MaxCombo": "587",
    "Acc": "7.12%",
    "Progress": "F Rank",
    "Clear": "Failed",
    "PlayTime": "2021-12-02 18:50:28"
  },
  {
    "UserID": "5965",
    "Nickname": "AnattA",
    "Cool": "1547",
    "Good": "1263",
    "Bad": "54",
    "Miss": "68",
    "MaxCombo": "603",
    "Acc": "6.87%",
    "Progress": "F Rank",
    "Clear": "Failed",
    "PlayTime": "2021-12-09 22:39:56"
  },
  {
    "UserID": "5524",
    "Nickname": "Cheyn",
    "Cool": "1901",
    "Good": "791",
    "Bad": "22",
    "Miss": "74",
    "MaxCombo": "471",
    "Acc": "6.6%",
    "Progress": "F Rank",
    "Clear": "Failed",
    "PlayTime": "2022-08-05 23:12:19"
  },
  {
    "UserID": "5853",
    "Nickname": "MoonSton",
    "Cool": "1786",
    "Good": "460",
    "Bad": "1",
    "Miss": "67",
    "MaxCombo": "757",
    "Acc": "5.51%",
    "Progress": "F Rank",
    "Clear": "Failed",
    "PlayTime": "2022-07-07 02:30:49"
  },
  {
    "UserID": "5609",
    "Nickname": "misuzu",
    "Cool": "1875",
    "Good": "326",
    "Bad": "4",
    "Miss": "83",
    "MaxCombo": "413",
    "Acc": "5.4%",
    "Progress": "F Rank",
    "Clear": "Failed",
    "PlayTime": "2022-11-25 22:07:35"
  },
  {
    "UserID": "6586",
    "Nickname": "Lovelyn",
    "Cool": "1871",
    "Good": "327",
    "Bad": "13",
    "Miss": "76",
    "MaxCombo": "316",
    "Acc": "5.39%",
    "Progress": "F Rank",
    "Clear": "Failed",
    "PlayTime": "2022-10-10 02:41:16"
  },
  {
    "UserID": "5360",
    "Nickname": "asdfunknown",
    "Cool": "1850",
    "Good": "347",
    "Bad": "15",
    "Miss": "72",
    "MaxCombo": "433",
    "Acc": "5.39%",
    "Progress": "F Rank",
    "Clear": "Failed",
    "PlayTime": "2021-02-07 15:05:39"
  },
  {
    "UserID": "5389",
    "Nickname": "Takumi",
    "Cool": "1672",
    "Good": "521",
    "Bad": "31",
    "Miss": "59",
    "MaxCombo": "386",
    "Acc": "5.38%",
    "Progress": "F Rank",
    "Clear": "Failed",
    "PlayTime": "2020-11-10 01:45:24"
  },
  {
    "UserID": "5376",
    "Nickname": "Cheese",
    "Cool": "1712",
    "Good": "480",
    "Bad": "25",
    "Miss": "67",
    "MaxCombo": "598",
    "Acc": "5.38%",
    "Progress": "F Rank",
    "Clear": "Failed",
    "PlayTime": "2022-08-11 22:31:11"
  },
  {
    "UserID": "5594",
    "Nickname": "예승이콩",
    "Cool": "1324",
    "Good": "807",
    "Bad": "25",
    "Miss": "63",
    "MaxCombo": "392",
    "Acc": "5.22%",
    "Progress": "F Rank",
    "Clear": "Failed",
    "PlayTime": "2021-12-27 02:04:02"
  },
  {
    "UserID": "5865",
    "Nickname": "SileN",
    "Cool": "1563",
    "Good": "560",
    "Bad": "7",
    "Miss": "66",
    "MaxCombo": "549",
    "Acc": "5.2%",
    "Progress": "F Rank",
    "Clear": "Failed",
    "PlayTime": "2022-03-30 19:34:47"
  },
  {
    "UserID": "5361",
    "Nickname": "2Coma",
    "Cool": "1710",
    "Good": "411",
    "Bad": "16",
    "Miss": "62",
    "MaxCombo": "485",
    "Acc": "5.2%",
    "Progress": "F Rank",
    "Clear": "Failed",
    "PlayTime": "2020-12-10 13:07:16"
  },
  {
    "UserID": "3327",
    "Nickname": "WNCC",
    "Cool": "1612",
    "Good": "501",
    "Bad": "41",
    "Miss": "62",
    "MaxCombo": "251",
    "Acc": "5.18%",
    "Progress": "F Rank",
    "Clear": "Failed",
    "PlayTime": "2020-11-10 01:45:24"
  },
  {
    "UserID": "5803",
    "Nickname": "티아고",
    "Cool": "1134",
    "Good": "965",
    "Bad": "47",
    "Miss": "54",
    "MaxCombo": "280",
    "Acc": "5.13%",
    "Progress": "F Rank",
    "Clear": "Failed",
    "PlayTime": "2021-03-03 05:25:23"
  },
  {
    "UserID": "5508",
    "Nickname": "pob",
    "Cool": "1434",
    "Good": "519",
    "Bad": "20",
    "Miss": "64",
    "MaxCombo": "462",
    "Acc": "4.79%",
    "Progress": "F Rank",
    "Clear": "Failed",
    "PlayTime": "2021-02-02 01:15:18"
  },
  {
    "UserID": "5378",
    "Nickname": "MachiFish",
    "Cool": "1420",
    "Good": "514",
    "Bad": "21",
    "Miss": "59",
    "MaxCombo": "676",
    "Acc": "4.74%",
    "Progress": "F Rank",
    "Clear": "Failed",
    "PlayTime": "2020-11-10 01:45:24"
  },
  {
    "UserID": "6391",
    "Nickname": "A2m",
    "Cool": "1329",
    "Good": "279",
    "Bad": "11",
    "Miss": "69",
    "MaxCombo": "174",
    "Acc": "3.94%",
    "Progress": "F Rank",
    "Clear": "Failed",
    "PlayTime": "2022-10-03 01:52:13"
  },
  {
    "UserID": "5930",
    "Nickname": "Notpx-",
    "Cool": "1436",
    "Good": "163",
    "Bad": "5",
    "Miss": "57",
    "MaxCombo": "396",
    "Acc": "3.93%",
    "Progress": "F Rank",
    "Clear": "Failed",
    "PlayTime": "2021-02-15 00:42:46"
  },
  {
    "UserID": "6006",
    "Nickname": "RUCO",
    "Cool": "1219",
    "Good": "362",
    "Bad": "28",
    "Miss": "54",
    "MaxCombo": "257",
    "Acc": "3.88%",
    "Progress": "F Rank",
    "Clear": "Failed",
    "PlayTime": "2022-02-21 06:12:28"
  },
  {
    "UserID": "6091",
    "Nickname": "Irvin",
    "Cool": "1150",
    "Good": "396",
    "Bad": "27",
    "Miss": "55",
    "MaxCombo": "303",
    "Acc": "3.79%",
    "Progress": "F Rank",
    "Clear": "Failed",
    "PlayTime": "2021-06-10 14:31:13"
  },
  {
    "UserID": "3333",
    "Nickname": "kraiz19",
    "Cool": "1325",
    "Good": "213",
    "Bad": "0",
    "Miss": "63",
    "MaxCombo": "281",
    "Acc": "3.77%",
    "Progress": "F Rank",
    "Clear": "Failed",
    "PlayTime": "2022-04-17 18:10:08"
  },
  {
    "UserID": "4341",
    "Nickname": "Ryuji1996",
    "Cool": "961",
    "Good": "526",
    "Bad": "20",
    "Miss": "49",
    "MaxCombo": "469",
    "Acc": "3.64%",
    "Progress": "F Rank",
    "Clear": "Failed",
    "PlayTime": "2022-11-20 02:59:34"
  },
  {
    "UserID": "2276",
    "Nickname": "bsc0626",
    "Cool": "1305",
    "Good": "156",
    "Bad": "8",
    "Miss": "55",
    "MaxCombo": "470",
    "Acc": "3.59%",
    "Progress": "F Rank",
    "Clear": "Failed",
    "PlayTime": "2022-05-15 17:54:23"
  },
  {
    "UserID": "5582",
    "Nickname": "궁상",
    "Cool": "1184",
    "Good": "241",
    "Bad": "25",
    "Miss": "46",
    "MaxCombo": "749",
    "Acc": "3.5%",
    "Progress": "F Rank",
    "Clear": "Failed",
    "PlayTime": "2020-11-28 22:05:43"
  },
  {
    "UserID": "5469",
    "Nickname": "GNIKHCIR",
    "Cool": "835",
    "Good": "590",
    "Bad": "16",
    "Miss": "51",
    "MaxCombo": "316",
    "Acc": "3.49%",
    "Progress": "F Rank",
    "Clear": "Failed",
    "PlayTime": "2020-11-10 01:45:24"
  },
  {
    "UserID": "5767",
    "Nickname": "Grinbi",
    "Cool": "1148",
    "Good": "166",
    "Bad": "0",
    "Miss": "37",
    "MaxCombo": "756",
    "Acc": "3.23%",
    "Progress": "F Rank",
    "Clear": "Failed",
    "PlayTime": "2021-03-25 16:38:27"
  },
  {
    "UserID": "6516",
    "Nickname": "AldenRitsards",
    "Cool": "497",
    "Good": "718",
    "Bad": "17",
    "Miss": "43",
    "MaxCombo": "317",
    "Acc": "2.97%",
    "Progress": "F Rank",
    "Clear": "Failed",
    "PlayTime": "2022-10-25 18:53:55"
  },
  {
    "UserID": "6016",
    "Nickname": "aid",
    "Cool": "941",
    "Good": "261",
    "Bad": "9",
    "Miss": "49",
    "MaxCombo": "277",
    "Acc": "2.95%",
    "Progress": "F Rank",
    "Clear": "Failed",
    "PlayTime": "2021-08-30 23:24:39"
  },
  {
    "UserID": "5628",
    "Nickname": "mgas",
    "Cool": "868",
    "Good": "333",
    "Bad": "7",
    "Miss": "43",
    "MaxCombo": "717",
    "Acc": "2.94%",
    "Progress": "F Rank",
    "Clear": "Failed",
    "PlayTime": "2021-04-07 22:39:31"
  },
  {
    "UserID": "5394",
    "Nickname": "Cypher",
    "Cool": "644",
    "Good": "531",
    "Bad": "37",
    "Miss": "44",
    "MaxCombo": "413",
    "Acc": "2.87%",
    "Progress": "F Rank",
    "Clear": "Failed",
    "PlayTime": "2022-03-30 00:34:44"
  },
  {
    "UserID": "5618",
    "Nickname": "Hades",
    "Cool": "738",
    "Good": "74",
    "Bad": "0",
    "Miss": "37",
    "MaxCombo": "500",
    "Acc": "1.99%",
    "Progress": "F Rank",
    "Clear": "Failed",
    "PlayTime": "2021-11-26 19:01:05"
  },
  {
    "UserID": "5368",
    "Nickname": "햇살",
    "Cool": "67",
    "Good": "14",
    "Bad": "0",
    "Miss": "34",
    "MaxCombo": "67",
    "Acc": "0.2%",
    "Progress": "F Rank",
    "Clear": "Failed",
    "PlayTime": "2020-11-10 01:45:24"
  }
]